Workbook

Sheet Lisez-moi
A1: Fichier de prospection YEBA FORMATIONS – 974 (5 octobre 2026)
A3: Comment l'utiliser
A4: • Cellules jaunes = à remplir (Statut, Date 1er contact, Notes). Exemple : Statut « Contacté », date 06/10/2026, note « standard : rappeler M. X jeudi ».
A5: • Filtrez par Priorité (1 = cibles les plus mûres : comptables, courtiers, immobilier, notaires, avocats) puis appelez le standard.
A6: • L'onglet « Synthèse » se met à jour seul.
A8: D'où viennent les données
A9: • Uniquement d'annuaires et de sites publics consultés le 05/10/2026 (colonne Source). Rien n'est inventé : une case vide = information non trouvée.
A10: • Vérifiez chaque numéro avant d'appeler (les annuaires ne sont pas toujours à jour). Complétez l'email depuis la page contact du site.
A11: • Pour une liste exhaustive (des milliers d'entreprises, avec SIREN et effectif) : lancez prospection/extraire_entreprises_974.py depuis votre ordinateur (API publique de l'État, bloquée sur mon serveur).
A13: RGPD (à respecter)
A14: • Seules des entreprises figurent ici : les entrepreneurs individuels et les noms de personnes ont été écartés (minimisation, art. 5 RGPD).
A15: • Email B2B : autorisé sans consentement si l'offre concerne la fonction du destinataire. Indiquez votre identité, la source des coordonnées et un moyen de s'opposer (art. 14 et 21 RGPD).
... A22: • OPCO « probable » : déduit de la convention collective habituelle du secteur ; à confirmer avec l'entreprise.

Sheet Prospects 974
A1: N° | B1: Entreprise | C1: Secteur | D1: Priorité | E1: Commune | F1: Adresse | G1: Téléphone standard | H1: Email générique | I1: Site web | J1: OPCO probable | K1: Accroche suggérée | L1: Statut | M1: Date 1er contact | N1: Notes | O1: Source | P1: Remarque vérifiée
A2: 1 | B2: Cabinet d'Avocats Nativel | C2: Cabinets d'avocats | D2: 1 | E2: Saint-Denis | F2: 3 rue Cité Jasmin ou 20 rue Saint-Jacques, 97400 (sources divergentes) ; bureau secondaire à Saint-Pierre | J2: OPCO EP | K2: Secret professionnel + IA générative : charte, outils souverains, formation des collaborateurs (OPCO EP). | L2: À qualifier | O2: https://www.annuaireavocats.fr/cabinets/droit-des-affaires/saint-denis-la-reunion ; https://gery-avocats-associes.fr/ | P2: Adresse à confirmer
A3: 2 | B3: Gery Avocats Associés | C3: Cabinets d'avocats | D3: 1 | E3: Saint-Denis | F3: 12 rue Labourdonnais, 97400 | I3: https://gery-avocats-associes.fr/ | J3: OPCO EP | K3: Secret professionnel + IA générative : charte, outils souverains, formation des collaborateurs (OPCO EP). | L3: À qualifier | O3: https://www.annuaireavocats.fr/cabinets/droit-des-affaires/saint-denis-la-reunion ; https://gery-avocats-associes.fr/
A4: 3 | B4: OCRE Avocats | C4: Cabinets d'avocats | D4: 1 | E4: Saint-Denis | F4: 74 rue Monthyon, 97400 | J4: OPCO EP | K4: Secret professionnel + IA générative : charte, outils souverains, formation des collaborateurs (OPCO EP). | L4: À qualifier | O4: https://www.annuaireavocats.fr/cabinets/droit-des-affaires/saint-denis-la-reunion ; https://gery-avocats-associes.fr/
A5: 4 | B5: Rivière – Delrieu & Associés | C5: Cabinets d'avocats | D5: 1 | E5: Saint-Denis | J5: OPCO EP | K5: Secret professionnel + IA générative : charte, outils souverains, formation des collaborateurs (OPCO EP). | L5: À qualifier | O5: https://www.annuaireavocats.fr/cabinets/droit-des-affaires/saint-denis-la-reunion ; https://gery-avocats-associes.fr/
A6: 5 | B6: Assurance Réunion Solutions | C6: Courtage & assurance | D6: 1 | E6: Saint-Denis | F6: Bât. Jardin de Juliette, 139 rue Juliette Dodu, 97400 | G6: 02 62 31 97 87 | J6: Atlas | K6: Données sensibles des assurés : usage maîtrisé de l'IA, RGPD et preuve de mesures art. 4 (OPCO Atlas). | L6: À qualifier | O6: https://www.pagesjaunes.fr/annuaire/saint-denis-974/assurances-courtiers ; https://www.assurco-assurance-reunion.fr/ ; https://www.courtierassurances.re/ ; https://www.cea-assurances.fr/nos-agences/agence-reunion/
A7: 6 | B7: Assurco | C7: Courtage & assurance | D7: 1 | E7: Saint-Denis | F7: 13 rue Charles Gounod, 97400 | G7: 02 62 94 13 65 | H7: direction@assurco.re | I7: https://www.assurco-assurance-reunion.fr/ | J7: Atlas | K7: Données sensibles des assurés : usage maîtrisé de l'IA, RGPD et preuve de mesures art. 4 (OPCO Atlas). | L7: À qualifier | O7: Recherche web 05/10/2026 (email direction@assurco.re cité avec le téléphone 0262941365) ; https://www.assurco-assurance-reunion.fr/ | P7: 4 agences sur l'île
A8: 7 | B8: CEA Réunion – Centre d'études d'assurances | C8: Courtage & assurance | D8: 1 | E8: Saint-Denis | F8: 98 rue Jules Auber, 97400 | I8: https://www.cea-assurances.fr/nos-agences/agence-reunion/ | J8: Atlas | K8: Données sensibles des assurés : usage maîtrisé de l'IA, RGPD et preuve de mesures art. 4 (OPCO Atlas). | L8: À qualifier | O8: https://www.pappers.fr/entreprise/439031857 ; https://www.cea-assurances.fr/nos-agences/agence-reunion/
A9: 8 | B9: Courtier Assurances | C9: Courtage & assurance | D9: 1 | E9: Saint-Denis | F9: 10 rue de Nice, 97400 | G9: 02 62 46 04 46 | I9: https://www.courtierassurances.re/ | J9: Atlas | K9: Données sensibles des assurés : usage maîtrisé de l'IA, RGPD et preuve de mesures art. 4 (OPCO Atlas). | L9: À qualifier | O9: https://www.pagesjaunes.fr/annuaire/saint-denis-974/assurances-courtiers ; https://www.assurco-assurance-reunion.fr/ ; https://www.courtierassurances.re/ ; https://www.cea-assurances.fr/nos-agences/agence-reunion/
A10: 9 | B10: Isautier Assurances | C10: Courtage & assurance | D10: 1 | E10: Saint-Denis | F10: 15 rue Juliette Dodu, 97400 | G10: 02 62 90 19 19 | J10: Atlas | K10: Données sensibles des assurés : usage maîtrisé de l'IA, RGPD et preuve de mesures art. 4 (OPCO Atlas). | L10: À qualifier | O10: https://www.pagesjaunes.fr/annuaire/saint-denis-974/assurances-courtiers ; https://www.assurco-assurance-reunion.fr/ ; https://www.courtierassurances.re/ ; https://www.cea-assurances.fr/nos-agences/agence-reunion/
A11: 10 | B11: JCS Courtage EURL | C11: Courtage & assurance | D11: 1 | E11: Saint-Denis | F11: 18 rue Ruisseau des Noirs, 97400 | G11: 02 62 97 59 71 | J11: Atlas | K11: Données sensibles des assurés : usage maîtrisé de l'IA, RGPD et preuve de mesures art. 4 (OPCO Atlas). | L11: À qualifier | O11: https://www.pagesjaunes.fr/annuaire/saint-denis-974/assurances-courtiers ; https://www.assurco-assurance-reunion.fr/ ; https://www.courtierassurances.re/ ; https://www.cea-assurances.fr/nos-agences/agence-reunion/
A12: 11 | B12: Réunion Assurances | C12: Courtage & assurance | D12: 1 | E12: Saint-Denis | F12: Bât. C Rés. Le Florentin, 45 av. Leconte de Lisle, 97490 | G12: 02 62 96 57 60 | J12: Atlas | K12: Données sensibles des assurés : usage maîtrisé de l'IA, RGPD et preuve de mesures art. 4 (OPCO Atlas). | L12: À qualifier | O12: https://www.pagesjaunes.fr/annuaire/saint-denis-974/assurances-courtiers ; https://www.assurco-assurance-reunion.fr/ ; https://www.courtierassurances.re/ ; https://www.cea-assurances.fr/nos-agences/agence-reunion/
A13: 12 | B13: AS Expertise Comptable | C13: Expertise comptable | D13: 1 | E13: Saint-Denis | F13: 41 rue Monthion, 97400 | J13: Atlas | K13: Vos collaborateurs saisissent-ils des données clients dans ChatGPT ? Formation IA + RGPD + charte d'usage, prise en charge OPCO Atlas. | L13: À qualifier | O13: https://fr.mappy.com/poi/5a6aa0500351d11fa08edb02 ; https://fr.mappy.com/poi/65e3e5aa00ef9c78bfaac72d
A14: 13 | B14: CCO Expertise | C14: Expertise comptable | D14: 1 | E14: Saint-Denis | F14: 14 ruelle Magnan, 97490 | G14: 02 62 97 89 03 | J14: Atlas | K14: Vos collaborateurs saisissent-ils des données clients dans ChatGPT ? Formation IA + RGPD + charte d'usage, prise en charge OPCO Atlas. | L14: À qualifier | O14: Recherche web 05/10/2026 – fiches Pages Jaunes (pagesjaunes.fr/pros/53172001, 63020050, 05903597) et https://www.pagesjaunes.fr/annuaire/departement/reunion-974/expertise-comptable
A15: 14 | B15: Cabinet AGCR Expertise Comptable | C15: Expertise comptable | D15: 1 | E15: Saint-Denis | F15: Rés. Anaxagore N°207, 24 rue Jean Cocteau, 97490 | G15: 02 62 20 65 00 | J15: Atlas | K15: Vos collaborateurs saisissent-ils des données clients dans ChatGPT ? Formation IA + RGPD + charte d'usage, prise en charge OPCO Atlas. | L15: À qualifier | O15: Recherche web 05/10/2026 – fiches Pages Jaunes (pagesjaunes.fr/pros/53172001, 63020050, 05903597) et https://www.pagesjaunes.fr/annuaire/departement/reunion-974/expertise-comptable | P15: 20 à 49 salariés : bonne taille pour un intra
A16: 15 | B16: Cabinet Ah Foune et Associés | C16: Expertise comptable | D16: 1 | E16: Saint-Denis | F16: 42 rue Jules Olivier ou 64 rue Roland Garros, 97400 (sources divergentes) | J16: Atlas | K16: Vos collaborateurs saisissent-ils des données clients dans ChatGPT ? Formation IA + RGPD + charte d'usage, prise en charge OPCO Atlas. | L16: À qualifier | O16: https://finalib.fr/expert/cabinet-ah-foune-et-associes-expert-comptable-saint-denis-a7eab0 ; https://www.pagesjaunes.fr/annuaire/departement/reunion-974/expertise-comptable | P16: Adresse à confirmer au premier appel
A17: 16 | B17: Casabona | C17: Expertise comptable | D17: 1 | E17: Saint-Pierre | F17: 7 allée Piscine, 97410 | J17: Atlas | K17: Vos collaborateurs saisissent-ils des données clients dans ChatGPT ? Formation IA + RGPD + charte d'usage, prise en charge OPCO Atlas. | L17: À qualifier | O17: https://comptable-lesexpertsdusud.re/ ; https://demarchesadministratives.fr/expert-comptable/saint-pierre-97410
A18: 17 | B18: D.C.A | C18: Expertise comptable | D18: 1 | E18: Saint-Denis | F18: 181 rue Jules Auber, 97400 | G18: 02 62 41 25 26 | J18: Atlas | K18: Vos collaborateurs saisissent-ils des données clients dans ChatGPT ? Formation IA + RGPD + charte d'usage, prise en charge OPCO Atlas. | L18: À qualifier | O18: Recherche web 05/10/2026 – fiches Pages Jaunes (pagesjaunes.fr/pros/53172001, 63020050, 05903597) et https://www.pagesjaunes.fr/annuaire/departement/reunion-974/expertise-comptable
A19: 18 | B19: EC Réunion | C19: Expertise comptable | D19: 1 | E19: Saint-Denis | F19: 248 rue Maréchal Leclerc, 97400 | G19: 02 62 93 88 88 | J19: Atlas | K19: Vos collaborateurs saisissent-ils des données clients dans ChatGPT ? Formation IA + RGPD + charte d'usage, prise en charge OPCO Atlas. | L19: À qualifier | O19: Recherche web 05/10/2026 – fiches Pages Jaunes (pagesjaunes.fr/pros/53172001, 63020050, 05903597) et https://www.pagesjaunes.fr/annuaire/departement/reunion-974/expertise-comptable
A20: 19 | B20: FIDUCIAL Expertise Saint-Denis | C20: Expertise comptable | D20: 1 | E20: Saint-Denis | F20: 6 rue de Lescouble, 97400 | G20: 02 62 72 18 50 | J20: Atlas | K20: Vos collaborateurs saisissent-ils des données clients dans ChatGPT ? Formation IA + RGPD + charte d'usage, prise en charge OPCO Atlas. | L20: À qualifier | O20: Recherche web 05/10/2026 – fiches Pages Jaunes (pagesjaunes.fr/pros/53172001, 63020050, 05903597) et https://www.pagesjaunes.fr/annuaire/departement/reunion-974/expertise-comptable
A21: 20 | B21: Les Experts du Sud | C21: Expertise comptable | D21: 1 | E21: Saint-Pierre | F21: 13 rue Bory Saint-Vincent, Rés. Guetali, ZAC Bank, 97410 | G21: 02 62 25 15 61 | I21: https://comptable-lesexpertsdusud.re/ | J21: Atlas | K21: Vos collaborateurs saisissent-ils des données clients dans ChatGPT ? Formation IA + RGPD + charte d'usage, prise en charge OPCO Atlas. | L21: À qualifier | O21: https://comptable-lesexpertsdusud.re/ ; https://demarchesadministratives.fr/expert-comptable/saint-pierre-97410
A22: 21 | B22: Medon & Associés | C22: Expertise comptable | D22: 1 | E22: Saint-Denis | F22: 21 rue Jules Auber, 97400 | I22: https://www.hlb.global/reunion | J22: Atlas | K22: Vos collaborateurs saisissent-ils des données clients dans ChatGPT ? Formation IA + RGPD + charte d'usage, prise en charge OPCO Atlas. | L22: À qualifier | O22: https://www.pappers.fr/entreprise/451726152 ; https://finalib.fr/expert/medon-associes-expert-comptable-saint-denis-51ae12 | P22: En procédure de sauvegarde depuis le 08/02/2026 : budget formation probablement gelé, pas prioritaire
A23: 22 | B23: Valentis Conseil & Audit | C23: Expertise comptable | D23: 1 | E23: Saint-Denis | F23: 22 chemin Dufourg les Bas, 97400 | J23: Atlas | K23: Vos collaborateurs saisissent-ils des données clients dans ChatGPT ? Formation IA + RGPD + charte d'usage, prise en charge OPCO Atlas. | L23: À qualifier | O23: https://fr.mappy.com/poi/5a6aa0500351d11fa08edb02 ; https://fr.mappy.com/poi/65e3e5aa00ef9c78bfaac72d
A24: 23 | B24: Getim | C24: Immobilier | D24: 1 | E24: Saint-Denis | F24: 4 avenue de la Victoire, 97400 (+ agence à Saint-Pierre) | G24: 02 62 21 12 61 | I24: https://www.getim.com/ | J24: À vérifier | K24: Annonces, comptes rendus de visite, réponses aux mandants : l'IA au service de l'agence, dans les règles RGPD. | L24: À qualifier | O24: https://www.orpi.com/mvsnord/ ; https://www.getim.com/ ; https://isautier.re/ ; https://www.sixiemeavenue.com/agences/saint-denis974/ ; https://kaze-immobilier.fr/ | P24: Attention : un homonyme « Getim » en Algérie apparaît dans les recherches d'email, ne pas confondre
A25: 24 | B25: Guy Hoquet Saint-Denis | C25: Immobilier | D25: 1 | E25: Saint-Denis | F25: 13 rue Charles Gounod, 97400 | G25: 02 62 41 66 00 | H25: saintdenis@guyhoquet.re | I25: https://la-reunion-saint-denis.guy-hoquet.com/ | J25: À vérifier | K25: Annonces, comptes rendus de visite, réponses aux mandants : l'IA au service de l'agence, dans les règles RGPD. | L25: À qualifier | O25: https://la-reunion-saint-denis.guy-hoquet.com/mon-agence ; https://la-reunion-saint-pierre.guy-hoquet.com/mon-agence
A26: 25 | B26: Guy Hoquet Saint-Pierre | C26: Immobilier | D26: 1 | E26: Saint-Pierre | F26: 78 bis bd Hubert Delisle, 97410 | G26: 02 62 27 90 90 | H26: saintpierre@guyhoquet.re | I26: https://la-reunion-saint-pierre.guy-hoquet.com/ | J26: À vérifier | K26: Annonces, comptes rendus de visite, réponses aux mandants : l'IA au service de l'agence, dans les règles RGPD. | L26: À qualifier | O26: https://la-reunion-saint-denis.guy-hoquet.com/mon-agence ; https://la-reunion-saint-pierre.guy-hoquet.com/mon-agence
A27: 26 | B27: Isautier Immobilier | C27: Immobilier | D27: 1 | E27: Saint-Denis | F27: 11 rue Juliette Dodu, 97400 | G27: 02 62 55 05 50 | I27: https://isautier.re/ | J27: À vérifier | K27: Annonces, comptes rendus de visite, réponses aux mandants : l'IA au service de l'agence, dans les règles RGPD. | L27: À qualifier | O27: https://www.orpi.com/mvsnord/ ; https://www.getim.com/ ; https://isautier.re/ ; https://www.sixiemeavenue.com/agences/saint-denis974/ ; https://kaze-immobilier.fr/
A28: 27 | B28: Kaze Immobilier | C28: Immobilier | D28: 1 | E28: Saint-Denis | I28: https://kaze-immobilier.fr/ | J28: À vérifier | K28: Annonces, comptes rendus de visite, réponses aux mandants : l'IA au service de l'agence, dans les règles RGPD. | L28: À qualifier | O28: https://www.orpi.com/mvsnord/ ; https://www.getim.com/ ; https://isautier.re/ ; https://www.sixiemeavenue.com/agences/saint-denis974/ ; https://kaze-immobilier.fr/
A29: 28 | B29: Orpi MVS (Saint-Denis, Saint-Gilles, Saint-Pierre) | C29: Immobilier | D29: 1 | E29: Saint-Denis | F29: 55 rue Labourdonnais, 97400 (+ 103 rue du Général de Gaulle, Saint-Gilles ; 30 rue de la Cayenne, Saint-Pierre) | G29: 02 62 51 74 74 | I29: https://www.orpi.com/mvs/ | J29: À vérifier | K29: Annonces, comptes rendus de visite, réponses aux mandants : l'IA au service de l'agence, dans les règles RGPD. | L29: À qualifier | O29: https://www.orpi.com/mvsnord/ ; https://www.getim.com/ ; https://isautier.re/ ; https://www.sixiemeavenue.com/agences/saint-denis974/ ; https://kaze-immobilier.fr/ | P29: 3 agences : proposer un intra commun
A30: 29 | B30: Sixième Avenue Saint-Denis | C30: Immobilier | D30: 1 | E30: Saint-Denis | I30: https://www.sixiemeavenue.com/agences/saint-denis974/ | J30: À vérifier | K30: Annonces, comptes rendus de visite, réponses aux mandants : l'IA au service de l'agence, dans les règles RGPD. | L30: À qualifier | O30: https://www.orpi.com/mvsnord/ ; https://www.getim.com/ ; https://isautier.re/ ; https://www.sixiemeavenue.com/agences/saint-denis974/ ; https://kaze-immobilier.fr/
A31: 30 | B31: NOT'AVENIR Notaires | C31: Notariat | D31: 1 | E31: Saint-Paul | F31: 8 rue Évariste de Parny, 97460 (+ Saint-Denis : 66 rue Labourdonnais, 02 62 73 08 08) | G31: 02 62 45 45 65 | I31: https://notavenir.notaires.fr/ | J31: OPCO EP | K31: Secret professionnel + IA : quelles pratiques autorisées ? Formation et charte pour l'étude (OPCO EP). | L31: À qualifier | O31: https://notavenir.notaires.fr/ ; https://notaires-pasteur.notaires.fr/ ; https://chambre-reunion.notaires.fr/notaire/
A32: 31 | B32: Notaires Pasteur | C32: Notariat | D32: 1 | E32: Saint-Denis | F32: 44 rue Pasteur, 97400 | G32: 02 62 90 14 14 | I32: https://notaires-pasteur.notaires.fr/ | J32: OPCO EP | K32: Secret professionnel + IA : quelles pratiques autorisées ? Formation et charte pour l'étude (OPCO EP). | L32: À qualifier | O32: https://notavenir.notaires.fr/ ; https://notaires-pasteur.notaires.fr/ ; https://chambre-reunion.notaires.fr/notaire/
A33: 32 | B33: Office notarial Aubert et associés | C33: Notariat | D33: 1 | E33: Saint-Pierre | F33: 32 rue Luc Lorion, 97453 Saint-Pierre Cedex | G33: 02 62 25 00 89 | J33: OPCO EP | K33: Secret professionnel + IA : quelles pratiques autorisées ? Formation et charte pour l'étude (OPCO EP). | L33: À qualifier | O33: https://notavenir.notaires.fr/ ; https://notaires-pasteur.notaires.fr/ ; https://chambre-reunion.notaires.fr/notaire/
A34: 33 | B34: Étude Gaudieux | C34: Notariat | D34: 1 | E34: Saint-Denis | F34: 62 bd du Chaudron, Centre d'affaires Cadjee, Bât. A, 9e ét., 97400 | G34: 02 62 15 08 40 | J34: OPCO EP | K34: Secret professionnel + IA : quelles pratiques autorisées ? Formation et charte pour l'étude (OPCO EP). | L34: À qualifier | O34: https://notavenir.notaires.fr/ ; https://notaires-pasteur.notaires.fr/ ; https://chambre-reunion.notaires.fr/notaire/
A35: 34 | B35: ABCD Mobilier | C35: Commerce de gros | D35: 2 | I35: https://www.abcd-mobilier.fr/ | J35: AKTO | K35: Devis, fiches produits, relances : 1 journée pour gagner du temps avec l'IA sans exposer vos données clients (OPCO AKTO). | L35: À qualifier | O35: https://www.pagesjaunes.fr/annuaire/departement/la-reunion-974/mobilier-de-bureau ; https://offital.com/ ; https://bureauxetobjets.com/
A36: 35 | B36: Adéquation Mobilier | C36: Commerce de gros | D36: 2 | E36: Saint-Denis | F36: 30 route Piton Bois de Nèfles | J36: AKTO | K36: Devis, fiches produits, relances : 1 journée pour gagner du temps avec l'IA sans exposer vos données clients (OPCO AKTO). | L36: À qualifier | O36: https://www.pagesjaunes.fr/annuaire/departement/la-reunion-974/mobilier-de-bureau ; https://offital.com/ ; https://bureauxetobjets.com/
A37: 36 | B37: BUROCA | C37: Commerce de gros | D37: 2 | E37: Sainte-Marie | F37: 6 rue Concorde, Innovespace A03 Duparc, 97438 | J37: AKTO | K37: Devis, fiches produits, relances : 1 journée pour gagner du temps avec l'IA sans exposer vos données clients (OPCO AKTO). | L37: À qualifier | O37: https://www.pagesjaunes.fr/annuaire/departement/la-reunion-974/mobilier-de-bureau ; https://offital.com/ ; https://bureauxetobjets.com/
A38: 37 | B38: BUROLIKE | C38: Commerce de gros | D38: 2 | E38: Sainte-Marie | F38: 2 rue du Soleil, PAE La Mare, 97438 | J38: AKTO | K38: Devis, fiches produits, relances : 1 journée pour gagner du temps avec l'IA sans exposer vos données clients (OPCO AKTO). | L38: À qualifier | O38: https://www.pagesjaunes.fr/annuaire/departement/la-reunion-974/mobilier-de-bureau ; https://offital.com/ ; https://bureauxetobjets.com/
A39: 38 | B39: Blanche Entreprises | C39: Commerce de gros | D39: 2 | E39: Saint-Denis | F39: 2 route Rivière des Pluies | J39: AKTO | K39: Devis, fiches produits, relances : 1 journée pour gagner du temps avec l'IA sans exposer vos données clients (OPCO AKTO). | L39: À qualifier | O39: https://www.pagesjaunes.fr/annuaire/departement/la-reunion-974/mobilier-de-bureau ; https://offital.com/ ; https://bureauxetobjets.com/
A40: 39 | B40: Bureaux & Objets Réunion | C40: Commerce de gros | D40: 2 | E40: Saint-Pierre | I40: https://bureauxetobjets.com/ | J40: AKTO | K40: Devis, fiches produits, relances : 1 journée pour gagner du temps avec l'IA sans exposer vos données clients (OPCO AKTO). | L40: À qualifier | O40: https://www.pagesjaunes.fr/annuaire/departement/la-reunion-974/mobilier-de-bureau ; https://offital.com/ ; https://bureauxetobjets.com/
A41: 40 | B41: CGF Distribution | C41: Commerce de gros | D41: 2 | E41: Le Port | J41: AKTO | K41: Devis, fiches produits, relances : 1 journée pour gagner du temps avec l'IA sans exposer vos données clients (OPCO AKTO). | L41: À qualifier | O41: https://fr.kompass.com/a/commerce-de-gros/81250/r/la-reunion/fr_04/ ; https://www.pagesjaunes.fr/annuaire/departement/la-reunion-974/alimentation-generale-gros
A42: 41 | B42: FAREN SAS | C42: Commerce de gros | D42: 2 | E42: Sainte-Marie | F42: 10 rue Soleil, 97438 | J42: AKTO | K42: Devis, fiches produits, relances : 1 journée pour gagner du temps avec l'IA sans exposer vos données clients (OPCO AKTO). | L42: À qualifier | O42: https://fr.kompass.com/a/commerce-de-gros/81250/r/la-reunion/fr_04/ ; https://www.pagesjaunes.fr/annuaire/departement/la-reunion-974/alimentation-generale-gros
A43: 42 | B43: Food Import Océan Indien | C43: Commerce de gros | D43: 2 | E43: Sainte-Marie | F43: 1 rue Général de Gaulle, 97438 | I43: https://foodimport-oi.re/ | J43: AKTO | K43: Devis, fiches produits, relances : 1 journée pour gagner du temps avec l'IA sans exposer vos données clients (OPCO AKTO). | L43: À qualifier | O43: https://foodimport-oi.re/
A44: 43 | B44: Offital (mobilier de bureau) | C44: Commerce de gros | D44: 2 | E44: Sainte-Marie | F44: 67 rue André Lardy, 97438 | I44: https://offital.com/ | J44: AKTO | K44: Devis, fiches produits, relances : 1 journée pour gagner du temps avec l'IA sans exposer vos données clients (OPCO AKTO). | L44: À qualifier | O44: https://www.pagesjaunes.fr/annuaire/departement/la-reunion-974/mobilier-de-bureau ; https://offital.com/ ; https://bureauxetobjets.com/
A45: 44 | B45: SDCOM | C45: Commerce de gros | D45: 2 | J45: AKTO | K45: Devis, fiches produits, relances : 1 journée pour gagner du temps avec l'IA sans exposer vos données clients (OPCO AKTO). | L45: À qualifier | O45: https://fr.kompass.com/a/commerce-de-gros/81250/r/la-reunion/fr_04/ ; https://www.pagesjaunes.fr/annuaire/departement/la-reunion-974/alimentation-generale-gros
A46: 45 | B46: SIDISRUN | C46: Commerce de gros | D46: 2 | E46: Sainte-Marie | F46: PAE La Mare, 97438 | J46: AKTO | K46: Devis, fiches produits, relances : 1 journée pour gagner du temps avec l'IA sans exposer vos données clients (OPCO AKTO). | L46: À qualifier | O46: https://fr.kompass.com/a/commerce-de-gros/81250/r/la-reunion/fr_04/ ; https://www.pagesjaunes.fr/annuaire/departement/la-reunion-974/alimentation-generale-gros
A47: 46 | B47: Socodiex | C47: Commerce de gros | D47: 2 | J47: AKTO | K47: Devis, fiches produits, relances : 1 journée pour gagner du temps avec l'IA sans exposer vos données clients (OPCO AKTO). | L47: À qualifier | O47: https://fr.kompass.com/a/commerce-de-gros/81250/r/la-reunion/fr_04/ ; https://www.pagesjaunes.fr/annuaire/departement/la-reunion-974/alimentation-generale-gros
A48: 47 | B48: Somadis | C48: Commerce de gros | D48: 2 | E48: Saint-Denis | F48: 98 rue de la République | J48: AKTO | K48: Devis, fiches produits, relances : 1 journée pour gagner du temps avec l'IA sans exposer vos données clients (OPCO AKTO). | L48: À qualifier | O48: https://www.pagesjaunes.fr/annuaire/departement/la-reunion-974/mobilier-de-bureau ; https://offital.com/ ; https://bureauxetobjets.com/
A49: 48 | B49: BNB | C49: Informatique / ESN | D49: 2 | I49: https://bnb.re/ | J49: Atlas | K49: Partenariat : vous déployez Copilot / M365, je forme les utilisateurs et sécurise RGPD / IA Act (OPCO Atlas). | L49: À qualifier | O49: https://mdsi.re/groupe-mdsi-fiche-entreprise/ ; https://ecureuil-digital.re/societe-informatique-reunion/ ; https://bnb.re/
A50: 49 | B50: Groupe MDSI | C50: Informatique / ESN | D50: 2 | E50: Le Port | I50: https://mdsi.re/ | J50: Atlas | K50: Partenariat : vous déployez Copilot / M365, je forme les utilisateurs et sécurise RGPD / IA Act (OPCO Atlas). | L50: À qualifier | O50: https://mdsi.re/groupe-mdsi-fiche-entreprise/ ; https://ecureuil-digital.re/societe-informatique-reunion/ ; https://bnb.re/
A51: 50 | B51: Écureuil Digital | C51: Informatique / ESN | D51: 2 | E51: Saint-Denis | F51: 3 agences : Saint-Denis, Saint-Paul, Saint-Pierre | I51: https://ecureuil-digital.re/ | J51: Atlas | K51: Partenariat : vous déployez Copilot / M365, je forme les utilisateurs et sécurise RGPD / IA Act (OPCO Atlas). | L51: À qualifier | O51: https://mdsi.re/groupe-mdsi-fiche-entreprise/ ; https://ecureuil-digital.re/societe-informatique-reunion/ ; https://bnb.re/
A52: 51 | B52: Alter Ego Océan Indien | C52: Intérim & recrutement | D52: 2 | F52: 4 agences sur l'île | J52: AKTO | K52: Tri de CV par IA = haut risque IA Act (annexe III) : audit + formation de vos chargés de recrutement. | L52: À qualifier | O52: https://www.pagesjaunes.fr/annuaire/saint-denis-974/agences-d-interim-et-d-emploi ; http://www.974job.com/agences ; https://www.randstad.fr/nos-agences/randstad-search-reunion_2970/
A53: 52 | B53: Axion | C53: Intérim & recrutement | D53: 2 | E53: Saint-Denis | F53: 30 rue Labourdonnais, 97400 | J53: AKTO | K53: Tri de CV par IA = haut risque IA Act (annexe III) : audit + formation de vos chargés de recrutement. | L53: À qualifier | O53: https://www.pagesjaunes.fr/annuaire/saint-denis-974/agences-d-interim-et-d-emploi ; http://www.974job.com/agences ; https://www.randstad.fr/nos-agences/randstad-search-reunion_2970/
A54: 53 | B54: Hooter & Event | C54: Intérim & recrutement | D54: 2 | E54: Saint-Denis | J54: AKTO | K54: Tri de CV par IA = haut risque IA Act (annexe III) : audit + formation de vos chargés de recrutement. | L54: À qualifier | O54: https://www.pagesjaunes.fr/annuaire/saint-denis-974/agences-d-interim-et-d-emploi ; http://www.974job.com/agences ; https://www.randstad.fr/nos-agences/randstad-search-reunion_2970/
A55: 54 | B55: Profil Océan Indien | C55: Intérim & recrutement | D55: 2 | E55: Saint-Denis | F55: 48 rue Général de Gaulle, 97400 | J55: AKTO | K55: Tri de CV par IA = haut risque IA Act (annexe III) : audit + formation de vos chargés de recrutement. | L55: À qualifier | O55: https://www.pagesjaunes.fr/annuaire/saint-denis-974/agences-d-interim-et-d-emploi ; http://www.974job.com/agences ; https://www.randstad.fr/nos-agences/randstad-search-reunion_2970/
A56: 55 | B56: Proman Gestion | C56: Intérim & recrutement | D56: 2 | E56: Saint-Denis | F56: 15 rue Pierre Aubert, Sainte-Clotilde, 97490 | J56: AKTO | K56: Tri de CV par IA = haut risque IA Act (annexe III) : audit + formation de vos chargés de recrutement. | L56: À qualifier | O56: https://www.pagesjaunes.fr/annuaire/saint-denis-974/agences-d-interim-et-d-emploi ; http://www.974job.com/agences ; https://www.randstad.fr/nos-agences/randstad-search-reunion_2970/
A57: 56 | B57: Randstad Search Réunion | C57: Intérim & recrutement | D57: 2 | E57: Saint-Denis | F57: 30 rue Labourdonnais, 97400 | I57: https://www.randstad.fr/nos-agences/randstad-search-reunion_2970/ | J57: AKTO | K57: Tri de CV par IA = haut risque IA Act (annexe III) : audit + formation de vos chargés de recrutement. | L57: À qualifier | O57: https://www.pagesjaunes.fr/annuaire/saint-denis-974/agences-d-interim-et-d-emploi ; http://www.974job.com/agences ; https://www.randstad.fr/nos-agences/randstad-search-reunion_2970/
A58: 57 | B58: Réunion Emploi Intérim | C58: Intérim & recrutement | D58: 2 | E58: Saint-Denis | F58: 45 av. Georges Brassens, Sainte-Clotilde, 97490 | J58: AKTO | K58: Tri de CV par IA = haut risque IA Act (annexe III) : audit + formation de vos chargés de recrutement. | L58: À qualifier | O58: https://www.pagesjaunes.fr/annuaire/saint-denis-974/agences-d-interim-et-d-emploi ; http://www.974job.com/agences ; https://www.randstad.fr/nos-agences/randstad-search-reunion_2970/
A59: 58 | B59: Service Intérim | C59: Intérim & recrutement | D59: 2 | J59: AKTO | K59: Tri de CV par IA = haut risque IA Act (annexe III) : audit + formation de vos chargés de recrutement. | L59: À qualifier | O59: https://www.pagesjaunes.fr/annuaire/saint-denis-974/agences-d-interim-et-d-emploi ; http://www.974job.com/agences ; https://www.randstad.fr/nos-agences/randstad-search-reunion_2970/
A60: 59 | B60: DSG Transit Repiquet | C60: Transport & logistique | D60: 2 | E60: Le Port | F60: ZAC Belvédère, 17 rue Roland Hoareau, 97420 | J60: OPCO Mobilités | K60: Suivi d'expéditions, documents douaniers, emails clients : prompts métiers et règles de confidentialité (OPCO Mobilités). | L60: À qualifier | O60: https://fr.kompass.com/s/transports-et-logistique/10/v/le-port/fr_04_974_97407/ ; https://www.pagesjaunes.fr/annuaire/le-port-974/transport-logistique
A61: 60 | B61: HOLDTRANS | C61: Transport & logistique | D61: 2 | E61: Le Port | F61: 2 rue Charles Darwin, 97420 | J61: OPCO Mobilités | K61: Suivi d'expéditions, documents douaniers, emails clients : prompts métiers et règles de confidentialité (OPCO Mobilités). | L61: À qualifier | O61: https://fr.kompass.com/s/transports-et-logistique/10/v/le-port/fr_04_974_97407/ ; https://www.pagesjaunes.fr/annuaire/le-port-974/transport-logistique
A62: 61 | B62: Le Transit Norgat Fils (TNF) | C62: Transport & logistique | D62: 2 | E62: Le Port | F62: 2 rue Émile Verhaeren, 97420 | J62: OPCO Mobilités | K62: Suivi d'expéditions, documents douaniers, emails clients : prompts métiers et règles de confidentialité (OPCO Mobilités). | L62: À qualifier | O62: https://fr.kompass.com/s/transports-et-logistique/10/v/le-port/fr_04_974_97407/ ; https://www.pagesjaunes.fr/annuaire/le-port-974/transport-logistique
A63: 62 | B63: SNT – Société Nouvelle de Transport | C63: Transport & logistique | D63: 2 | E63: Le Port | J63: OPCO Mobilités | K63: Suivi d'expéditions, documents douaniers, emails clients : prompts métiers et règles de confidentialité (OPCO Mobilités). | L63: À qualifier | O63: https://fr.kompass.com/s/transports-et-logistique/10/v/le-port/fr_04_974_97407/ ; https://www.pagesjaunes.fr/annuaire/le-port-974/transport-logistique
A64: 63 | B64: Schenker France (agence Réunion) | C64: Transport & logistique | D64: 2 | E64: Le Port | F64: 4 bis rue Paul Verlaine, 97420 | J64: OPCO Mobilités | K64: Suivi d'expéditions, documents douaniers, emails clients : prompts métiers et règles de confidentialité (OPCO Mobilités). | L64: À qualifier | O64: https://fr.kompass.com/s/transports-et-logistique/10/v/le-port/fr_04_974_97407/ ; https://www.pagesjaunes.fr/annuaire/le-port-974/transport-logistique
A65: 64 | B65: Sifa Réunion (Réunion Transit) | C65: Transport & logistique | D65: 2 | E65: Le Port | F65: ZI n°3, 30 rue Sully Prud'homme, 97420 | J65: OPCO Mobilités | K65: Suivi d'expéditions, documents douaniers, emails clients : prompts métiers et règles de confidentialité (OPCO Mobilités). | L65: À qualifier | O65: https://fr.kompass.com/s/transports-et-logistique/10/v/le-port/fr_04_974_97407/ ; https://www.pagesjaunes.fr/annuaire/le-port-974/transport-logistique
A66: 65 | B66: Société Nouvelle Legarnisson (SNL) | C66: Transport & logistique | D66: 2 | E66: Le Port | F66: 21 rue Camille Desmoulins, 97420 | J66: OPCO Mobilités | K66: Suivi d'expéditions, documents douaniers, emails clients : prompts métiers et règles de confidentialité (OPCO Mobilités). | L66: À qualifier | O66: https://fr.kompass.com/s/transports-et-logistique/10/v/le-port/fr_04_974_97407/ ; https://www.pagesjaunes.fr/annuaire/le-port-974/transport-logistique
A67: 66 | B67: Transit Azélie C (TAC) | C67: Transport & logistique | D67: 2 | E67: Le Port | F67: 21 rue Léon de Lépervanche, 97420 | J67: OPCO Mobilités | K67: Suivi d'expéditions, documents douaniers, emails clients : prompts métiers et règles de confidentialité (OPCO Mobilités). | L67: À qualifier | O67: https://fr.kompass.com/s/transports-et-logistique/10/v/le-port/fr_04_974_97407/ ; https://www.pagesjaunes.fr/annuaire/le-port-974/transport-logistique
A68: 67 | B68: Air Voyages | C68: Agences de voyages | D68: 3 | E68: Saint-Denis | F68: 7 rue Charles Gounod, 97400 (+ 40 rue des Bons Enfants, Saint-Pierre) | I68: https://www.airvoyages.fr/nos-agences | J68: À vérifier | K68: Programmes sur mesure, devis et emails clients en quelques minutes, sans fuite de données. | L68: À qualifier | O68: https://www.pagesjaunes.fr/annuaire/departement/la-reunion-974/agences-de-voyages ; https://www.airvoyages.fr/nos-agences ; https://www.selectour.com/agence/la-reunion/saint-denis/euro-voyages/13703
A69: 68 | B69: Bluesky | C69: Agences de voyages | D69: 3 | E69: Saint-Denis | F69: 74 rue Juliette Dodu, 97400 | J69: À vérifier | K69: Programmes sur mesure, devis et emails clients en quelques minutes, sans fuite de données. | L69: À qualifier | O69: https://www.pagesjaunes.fr/annuaire/departement/la-reunion-974/agences-de-voyages ; https://www.airvoyages.fr/nos-agences ; https://www.selectour.com/agence/la-reunion/saint-denis/euro-voyages/13703
A70: 69 | B70: Euro Voyages (Selectour) | C70: Agences de voyages | D70: 3 | E70: Saint-Denis | F70: 34 rue Issop Ravate, 97400 | I70: https://www.selectour.com/agence/la-reunion/saint-denis/euro-voyages/13703 | J70: À vérifier | K70: Programmes sur mesure, devis et emails clients en quelques minutes, sans fuite de données. | L70: À qualifier | O70: https://www.pagesjaunes.fr/annuaire/departement/la-reunion-974/agences-de-voyages ; https://www.airvoyages.fr/nos-agences ; https://www.selectour.com/agence/la-reunion/saint-denis/euro-voyages/13703
A71: 70 | B71: Havas Voyages Réunion | C71: Agences de voyages | D71: 3 | E71: Saint-Denis | F71: 114 rue Juliette Dodu, 97400 | J71: À vérifier | K71: Programmes sur mesure, devis et emails clients en quelques minutes, sans fuite de données. | L71: À qualifier | O71: https://www.pagesjaunes.fr/annuaire/departement/la-reunion-974/agences-de-voyages ; https://www.airvoyages.fr/nos-agences ; https://www.selectour.com/agence/la-reunion/saint-denis/euro-voyages/13703
A72: 71 | B72: Marines Voyages | C72: Agences de voyages | D72: 3 | E72: Saint-Pierre | F72: 1 boulevard Bank, 97410 | J72: À vérifier | K72: Programmes sur mesure, devis et emails clients en quelques minutes, sans fuite de données. | L72: À qualifier | O72: https://www.pagesjaunes.fr/annuaire/departement/la-reunion-974/agences-de-voyages ; https://www.airvoyages.fr/nos-agences ; https://www.selectour.com/agence/la-reunion/saint-denis/euro-voyages/13703
A73: 72 | B73: Odyssée | C73: Agences de voyages | D73: 3 | E73: Saint-Denis | F73: 56 rue Jules Auber, 97400 | J73: À vérifier | K73: Programmes sur mesure, devis et emails clients en quelques minutes, sans fuite de données. | L73: À qualifier | O73: https://www.pagesjaunes.fr/annuaire/departement/la-reunion-974/agences-de-voyages ; https://www.airvoyages.fr/nos-agences ; https://www.selectour.com/agence/la-reunion/saint-denis/euro-voyages/13703
A74: 73 | B74: Transcontinents | C74: Agences de voyages | D74: 3 | E74: Saint-Denis | F74: 248 rue du Maréchal Leclerc, 97400 (+ 18 bd Hubert Delisle, Saint-Pierre) | J74: À vérifier | K74: Programmes sur mesure, devis et emails clients en quelques minutes, sans fuite de données. | L74: À qualifier | O74: https://www.pagesjaunes.fr/annuaire/departement/la-reunion-974/agences-de-voyages ; https://www.airvoyages.fr/nos-agences ; https://www.selectour.com/agence/la-reunion/saint-denis/euro-voyages/13703
A75: 74 | B75: Voyages Réunion | C75: Agences de voyages | D75: 3 | E75: Saint-Pierre | F75: C. Cial Grand Large, allée Petit Paris, 97410 | J75: À vérifier | K75: Programmes sur mesure, devis et emails clients en quelques minutes, sans fuite de données. | L75: À qualifier | O75: https://www.pagesjaunes.fr/annuaire/departement/la-reunion-974/agences-de-voyages ; https://www.airvoyages.fr/nos-agences ; https://www.selectour.com/agence/la-reunion/saint-denis/euro-voyages/13703
A76: 75 | B76: Yes We Can Travel | C76: Agences de voyages | D76: 3 | E76: Saint-Denis | F76: 5 rue Charles Gounod, 97400 | J76: À vérifier | K76: Programmes sur mesure, devis et emails clients en quelques minutes, sans fuite de données. | L76: À qualifier | O76: https://www.pagesjaunes.fr/annuaire/departement/la-reunion-974/agences-de-voyages ; https://www.airvoyages.fr/nos-agences ; https://www.selectour.com/agence/la-reunion/saint-denis/euro-voyages/13703
A77: 76 | B77: Automobiles Réunion SN – Renault / Dacia | C77: Automobile | D77: 3 | E77: Le Port | F77: ZAC 2000, 15 rue Charles Darwin, 97420 | J77: OPCO Mobilités | K77: Relances clients, annonces VO, réponses aux avis : l'IA pour vos équipes commerciales et après-vente (OPCO Mobilités). | L77: À qualifier | O77: https://www.reunion-directory.com/professions/automobile-concessions-agents-.html ; https://www.pagesjaunes.fr/pros/07476950
A78: 77 | B78: Bamytrucks (Mercedes-Benz Trucks, Iveco, DAF) | C78: Automobile | D78: 3 | E78: Le Port | J78: OPCO Mobilités | K78: Relances clients, annonces VO, réponses aux avis : l'IA pour vos équipes commerciales et après-vente (OPCO Mobilités). | L78: À qualifier | O78: https://www.reunion-directory.com/professions/automobile-concessions-agents-.html ; https://www.pagesjaunes.fr/pros/07476950
A79: 78 | B79: CAT (Nissan, Seat, Honda, Opel…) | C79: Automobile | D79: 3 | E79: Saint-Denis | J79: OPCO Mobilités | K79: Relances clients, annonces VO, réponses aux avis : l'IA pour vos équipes commerciales et après-vente (OPCO Mobilités). | L79: À qualifier | O79: https://www.reunion-directory.com/professions/automobile-concessions-agents-.html ; https://www.pagesjaunes.fr/pros/07476950
A80: 79 | B80: CMM Automobiles (groupe CFAO) – Toyota, Ford, Volvo | C80: Automobile | D80: 3 | E80: Le Port | F80: 4 chemin des Anglais, 97420 (+ 4 chemin du Grand Canal, Saint-Denis) | J80: OPCO Mobilités | K80: Relances clients, annonces VO, réponses aux avis : l'IA pour vos équipes commerciales et après-vente (OPCO Mobilités). | L80: À qualifier | O80: https://www.reunion-directory.com/professions/automobile-concessions-agents-.html ; https://www.pagesjaunes.fr/pros/07476950
A81: 80 | B81: Hyundai Réunion | C81: Automobile | D81: 3 | E81: Saint-Denis | J81: OPCO Mobilités | K81: Relances clients, annonces VO, réponses aux avis : l'IA pour vos équipes commerciales et après-vente (OPCO Mobilités). | L81: À qualifier | O81: https://www.reunion-directory.com/professions/automobile-concessions-agents-.html ; https://www.pagesjaunes.fr/pros/07476950
A82: 81 | B82: JS Auto 974 | C82: Automobile | D82: 3 | I82: https://www.jsauto974.com/ | J82: OPCO Mobilités | K82: Relances clients, annonces VO, réponses aux avis : l'IA pour vos équipes commerciales et après-vente (OPCO Mobilités). | L82: À qualifier | O82: https://www.reunion-directory.com/professions/automobile-concessions-agents-.html ; https://www.pagesjaunes.fr/pros/07476950
A83: 82 | B83: Leal Réunion (BMW, Mini) | C83: Automobile | D83: 3 | E83: Saint-Denis | J83: OPCO Mobilités | K83: Relances clients, annonces VO, réponses aux avis : l'IA pour vos équipes commerciales et après-vente (OPCO Mobilités). | L83: À qualifier | O83: https://www.reunion-directory.com/professions/automobile-concessions-agents-.html ; https://www.pagesjaunes.fr/pros/07476950
A84: 83 | B84: Archipel (résidence hôtelière) | C84: Hôtellerie | D84: 3 | E84: Saint-Paul | F84: Saint-Gilles-les-Bains | J84: AKTO | K84: Réponses aux avis, emails multilingues, fiches séjour : l'IA pour vos équipes de réception (OPCO AKTO). | L84: À qualifier | O84: https://www.reunion.fr/organisez/vos-activites/le-tour-de-l-ile-de-la-reunion/les-etapes-incontournables/saint-denis/hotels-4-etoiles-saint-denis/ ; https://hotels.ile-delareunion.com/fr/hotels-3-etoiles/
A85: 84 | B85: Golden Tulip Sainte-Clotilde | C85: Hôtellerie | D85: 3 | E85: Saint-Denis | I85: https://www.goldentulip.com/en-us/our-hotels/la-reunion/hotels-saint-denis/ | J85: AKTO | K85: Réponses aux avis, emails multilingues, fiches séjour : l'IA pour vos équipes de réception (OPCO AKTO). | L85: À qualifier | O85: https://www.reunion.fr/organisez/vos-activites/le-tour-de-l-ile-de-la-reunion/les-etapes-incontournables/saint-denis/hotels-4-etoiles-saint-denis/ ; https://hotels.ile-delareunion.com/fr/hotels-3-etoiles/
A86: 85 | B86: Hôtel Austral by Exsel | C86: Hôtellerie | D86: 3 | E86: Saint-Denis | J86: AKTO | K86: Réponses aux avis, emails multilingues, fiches séjour : l'IA pour vos équipes de réception (OPCO AKTO). | L86: À qualifier | O86: https://www.reunion.fr/organisez/vos-activites/le-tour-de-l-ile-de-la-reunion/les-etapes-incontournables/saint-denis/hotels-4-etoiles-saint-denis/ ; https://hotels.ile-delareunion.com/fr/hotels-3-etoiles/
A87: 86 | B87: Hôtel Exsel Créolia | C87: Hôtellerie | D87: 3 | E87: Saint-Denis | J87: AKTO | K87: Réponses aux avis, emails multilingues, fiches séjour : l'IA pour vos équipes de réception (OPCO AKTO). | L87: À qualifier | O87: https://www.reunion.fr/organisez/vos-activites/le-tour-de-l-ile-de-la-reunion/les-etapes-incontournables/saint-denis/hotels-4-etoiles-saint-denis/ ; https://hotels.ile-delareunion.com/fr/hotels-3-etoiles/
A88: 87 | B88: Hôtel Exsel Ermitage | C88: Hôtellerie | D88: 3 | E88: Saint-Paul | F88: Saint-Gilles-les-Bains | J88: AKTO | K88: Réponses aux avis, emails multilingues, fiches séjour : l'IA pour vos équipes de réception (OPCO AKTO). | L88: À qualifier | O88: https://www.reunion.fr/organisez/vos-activites/le-tour-de-l-ile-de-la-reunion/les-etapes-incontournables/saint-denis/hotels-4-etoiles-saint-denis/ ; https://hotels.ile-delareunion.com/fr/hotels-3-etoiles/
A89: 88 | B89: Le Boucan Canot | C89: Hôtellerie | D89: 3 | E89: Saint-Paul | F89: Boucan Canot | J89: AKTO | K89: Réponses aux avis, emails multilingues, fiches séjour : l'IA pour vos équipes de réception (OPCO AKTO). | L89: À qualifier | O89: https://www.reunion.fr/organisez/vos-activites/le-tour-de-l-ile-de-la-reunion/les-etapes-incontournables/saint-denis/hotels-4-etoiles-saint-denis/ ; https://hotels.ile-delareunion.com/fr/hotels-3-etoiles/
A90: 89 | B90: Le Juliette Dodu | C90: Hôtellerie | D90: 3 | E90: Saint-Denis | J90: AKTO | K90: Réponses aux avis, emails multilingues, fiches séjour : l'IA pour vos équipes de réception (OPCO AKTO). | L90: À qualifier | O90: https://www.reunion.fr/organisez/vos-activites/le-tour-de-l-ile-de-la-reunion/les-etapes-incontournables/saint-denis/hotels-4-etoiles-saint-denis/ ; https://hotels.ile-delareunion.com/fr/hotels-3-etoiles/
A91: 90 | B91: Le Récif Saint-Gilles (groupe LUX*) | C91: Hôtellerie | D91: 3 | E91: Saint-Paul | F91: Saint-Gilles-les-Bains | J91: AKTO | K91: Réponses aux avis, emails multilingues, fiches séjour : l'IA pour vos équipes de réception (OPCO AKTO). | L91: À qualifier | O91: https://www.reunion.fr/organisez/vos-activites/le-tour-de-l-ile-de-la-reunion/les-etapes-incontournables/saint-denis/hotels-4-etoiles-saint-denis/ ; https://hotels.ile-delareunion.com/fr/hotels-3-etoiles/
A92: 91 | B92: Radisson Hôtel Saint-Denis | C92: Hôtellerie | D92: 3 | E92: Saint-Denis | J92: AKTO | K92: Réponses aux avis, emails multilingues, fiches séjour : l'IA pour vos équipes de réception (OPCO AKTO). | L92: À qualifier | O92: https://www.reunion.fr/organisez/vos-activites/le-tour-de-l-ile-de-la-reunion/les-etapes-incontournables/saint-denis/hotels-4-etoiles-saint-denis/ ; https://hotels.ile-delareunion.com/fr/hotels-3-etoiles/
A93: 92 | B93: Relais de l'Hermitage | C93: Hôtellerie | D93: 3 | E93: Saint-Paul | F93: Saint-Gilles-les-Bains | I93: https://www.relais-hermitage-saintgilles.fr/en/ | J93: AKTO | K93: Réponses aux avis, emails multilingues, fiches séjour : l'IA pour vos équipes de réception (OPCO AKTO). | L93: À qualifier | O93: https://www.reunion.fr/organisez/vos-activites/le-tour-de-l-ile-de-la-reunion/les-etapes-incontournables/saint-denis/hotels-4-etoiles-saint-denis/ ; https://hotels.ile-delareunion.com/fr/hotels-3-etoiles/
A94: 93 | B94: Tama Hôtel | C94: Hôtellerie | D94: 3 | E94: Saint-Paul | F94: Saint-Gilles-les-Bains | J94: AKTO | K94: Réponses aux avis, emails multilingues, fiches séjour : l'IA pour vos équipes de réception (OPCO AKTO). | L94: À qualifier | O94: https://www.reunion.fr/organisez/vos-activites/le-tour-de-l-ile-de-la-reunion/les-etapes-incontournables/saint-denis/hotels-4-etoiles-saint-denis/ ; https://hotels.ile-delareunion.com/fr/hotels-3-etoiles/
A95: 94 | B95: Tropic Appart Hôtel | C95: Hôtellerie | D95: 3 | E95: Saint-Paul | F95: Saint-Gilles-les-Bains | J95: AKTO | K95: Réponses aux avis, emails multilingues, fiches séjour : l'IA pour vos équipes de réception (OPCO AKTO). | L95: À qualifier | O95: https://www.reunion.fr/organisez/vos-activites/le-tour-de-l-ile-de-la-reunion/les-etapes-incontournables/saint-denis/hotels-4-etoiles-saint-denis/ ; https://hotels.ile-delareunion.com/fr/hotels-3-etoiles/
A96: 95 | B96: Brasserie Dalons | C96: Agroalimentaire | D96: 4 | J96: OCAPIAT | K96: Qualité, traçabilité, documents réglementaires : l'IA pour les fonctions support (OPCO OCAPIAT). | L96: À qualifier | O96: https://fr.wikipedia.org/wiki/Association_pour_le_d%C3%A9veloppement_industriel_de_La_R%C3%A9union ; https://adir.re/
A97: 96 | B97: Distillerie Chatel | C97: Agroalimentaire | D97: 4 | J97: OCAPIAT | K97: Qualité, traçabilité, documents réglementaires : l'IA pour les fonctions support (OPCO OCAPIAT). | L97: À qualifier | O97: https://fr.wikipedia.org/wiki/Association_pour_le_d%C3%A9veloppement_industriel_de_La_R%C3%A9union ; https://adir.re/
A98: 97 | B98: Distillerie Rivière du Mât | C98: Agroalimentaire | D98: 4 | J98: OCAPIAT | K98: Qualité, traçabilité, documents réglementaires : l'IA pour les fonctions support (OPCO OCAPIAT). | L98: À qualifier | O98: https://fr.wikipedia.org/wiki/Association_pour_le_d%C3%A9veloppement_industriel_de_La_R%C3%A9union ; https://adir.re/
A99: 98 | B99: Groupe Cilam | C99: Agroalimentaire | D99: 4 | J99: OCAPIAT | K99: Qualité, traçabilité, documents réglementaires : l'IA pour les fonctions support (OPCO OCAPIAT). | L99: À qualifier | O99: https://fr.wikipedia.org/wiki/Association_pour_le_d%C3%A9veloppement_industriel_de_La_R%C3%A9union ; https://adir.re/
A100: 99 | B100: Mascarin | C100: Agroalimentaire | D100: 4 | J100: OCAPIAT | K100: Qualité, traçabilité, documents réglementaires : l'IA pour les fonctions support (OPCO OCAPIAT). | L100: À qualifier | O100: https://fr.wikipedia.org/wiki/Association_pour_le_d%C3%A9veloppement_industriel_de_La_R%C3%A9union ; https://adir.re/
...

Sheet Grands comptes
A1: Groupe | B1: Secteur | C1: Repère | D1: Approche conseillée | E1: Statut | F1: Source
A2: Groupe Bernard Hayot (GBH) | B2: Distribution, automobile, industrie | C2: 1er groupe privé de l'île (≈ 7 100 salariés, ≈ 1,9 Md€ de CA selon le classement) | D2: Contacter la DRH / le responsable formation ; souvent achat par consultation : proposer un pilote d'une journée « Pack Article 4 » pour un service. | E2: À qualifier | F2: https://www.marketing-management.io/blog/top-40-entreprises-a-la-reunion
A3: Vindémia | B3: Grande distribution | C3: Top 10 | D3: Contacter la DRH / le responsable formation ; souvent achat par consultation : proposer un pilote d'une journée « Pack Article 4 » pour un service. | E3: À qualifier | F3: https://www.marketing-management.io/blog/top-40-entreprises-a-la-reunion
A4: Groupe Caillé | B4: Automobile, distribution | C4: Top 10 (≈ 623 M€ de CA) | D4: Contacter la DRH / le responsable formation ; souvent achat par consultation : proposer un pilote d'une journée « Pack Article 4 » pour un service. | E4: À qualifier | F4: https://www.marketing-management.io/blog/top-40-entreprises-a-la-reunion
A5: Groupe Excellence | B5: Automobile | C5: Top 10 | D5: Contacter la DRH / le responsable formation ; souvent achat par consultation : proposer un pilote d'une journée « Pack Article 4 » pour un service. | E5: À qualifier | F5: https://www.marketing-management.io/blog/top-40-entreprises-a-la-reunion
A6: Air Austral | B6: Transport aérien | C6: Top 10 | D6: Contacter la DRH / le responsable formation ; souvent achat par consultation : proposer un pilote d'une journée « Pack Article 4 » pour un service. | E6: À qualifier | F6: https://www.marketing-management.io/blog/top-40-entreprises-a-la-reunion
A7: Groupe Ravate | B7: Distribution | C7: Top 10 | D7: Contacter la DRH / le responsable formation ; souvent achat par consultation : proposer un pilote d'une journée « Pack Article 4 » pour un service. | E7: À qualifier | F7: https://www.marketing-management.io/blog/top-40-entreprises-a-la-reunion
A8: Groupe Marbour | B8: Distribution | C8: Top 10 | D8: Contacter la DRH / le responsable formation ; souvent achat par consultation : proposer un pilote d'une journée « Pack Article 4 » pour un service. | E8: À qualifier | F8: https://www.marketing-management.io/blog/top-40-entreprises-a-la-reunion
A9: Groupe Urcoopa | B9: Agroalimentaire, coopérative | C9: Top 10 | D9: Contacter la DRH / le responsable formation ; souvent achat par consultation : proposer un pilote d'une journée « Pack Article 4 » pour un service. | E9: À qualifier | F9: https://www.marketing-management.io/blog/top-40-entreprises-a-la-reunion
A10: Tereos Océan Indien | B10: Sucre, industrie | C10: Top 10 | D10: Contacter la DRH / le responsable formation ; souvent achat par consultation : proposer un pilote d'une journée « Pack Article 4 » pour un service. | E10: À qualifier | F10: https://www.marketing-management.io/blog/top-40-entreprises-a-la-reunion
A11: Groupe Océinde | B11: Énergie, distribution | C11: ≈ 360 M€ de CA | D11: Contacter la DRH / le responsable formation ; souvent achat par consultation : proposer un pilote d'une journée « Pack Article 4 » pour un service. | E11: À qualifier | F11: https://www.marketing-management.io/blog/top-40-entreprises-a-la-reunion
A12: Coopérative U La Réunion | B12: Grande distribution | C12: Classement 2025 | D12: Contacter la DRH / le responsable formation ; souvent achat par consultation : proposer un pilote d'une journée « Pack Article 4 » pour un service. | E12: À qualifier | F12: https://www.marketing-management.io/blog/top-40-entreprises-a-la-reunion
... A14: ADIR (Association pour le développement industriel) | B14: Réseau de ≈ 200 industriels | C14: Prescripteur : intervention lors d'un événement adhérents | D14: Contacter la DRH / le responsable formation ; souvent achat par consultation : proposer un pilote d'une journée « Pack Article 4 » pour un service. | E14: À qualifier | F14: https://adir.re/

Sheet Sous-traitance OF
A1: Organisme | B1: Zone | C1: Type | D1: Domaines | E1: Adresse | F1: Téléphone | G1: Email | H1: Site web | I1: Pourquoi vous / action | J1: Priorité | K1: Statut | L1: Date candidature | M1: Source
A2: Honoris Educational Network | B2: Maurice | C2: Organisme agréé MQA | D2: Soft skills, Microsoft Office, automatisation, data, marketing digital | H2: https://honoris.ac.mu/mqa-approved-training-programmes-mauritius/ | I2: Partenariat : formation IA éligible au remboursement HRDC jusqu'à 90 % | J2: A | K2: À contacter | M2: https://honoris.ac.mu/mqa-approved-training-programmes-mauritius/
A3: SMFP – Société mahoraise de formation professionnelle | B3: Mayotte – Mamoudzou | C3: OF 976 (Qualiopi) | D3: Numérique (CléA), social | E3: Mamoudzou | H3: https://www.smfp-site.fr/ | I3: Numérique + IA à Mayotte (AAP France 2030 Mayotte ouvert jusqu'au 31/12/2026) | J3: A | K3: À contacter | M3: https://www.intercariforef.org/formations/societe-mahoraise-de-formation-professionnelle-smfp/organisme-39_216.html
A4: Senza Formations | B4: Métropole → 974 | C4: OF national, sessions à Saint-Denis | D4: IA générative | E4: Sessions à Saint-Denis (28/09-28/10 et 30/11-30/12/2026) | H4: https://senza-formations.com/ville/saint-denis/formation-initiation-lintelligence-artificielle-ia | I4: Programme des sessions IA à Saint-Denis : il leur faut un formateur local | J4: A | K4: À contacter | M4: https://senza-formations.com/ville/saint-denis/formation-initiation-lintelligence-artificielle-ia
A5: VIAgence | B5: Métropole → 974 | C5: OF qui vend dans le 974 | D5: IA | E5: 32 rue de Paris, 92100 Boulogne-Billancourt | F5: 01 79 35 52 37 | G5: contact@viagence.com | I5: Vend du présentiel à Saint-Denis sans être implanté : proposez-vous comme formateur sur place (modèle d'email dans opportunites.md) | J5: A | K5: À contacter | M5: Programme reçu par votre amie
A6: A'Venir | B6: Réunion | C6: OF 974 (Qualiopi) | D6: Passerelle IA | H6: https://a-venir.re/ | I6: Co-animation « Passerelle IA » | J6: A | K6: À contacter | M6: https://a-venir.re/
A7: CCI Réunion (+ CFA Campus Pro Saint-Pierre) | B7: Réunion | C7: Consulaire | D7: IA et productivité, commerce, vente, gestion | E7: CFA : 65 rue du Père Lafosse, 97410 Saint-Pierre | H7: https://reunion.cci.fr/formation/166206/ia-et-productivite-outils-et-bonnes-pratiques | I7: Catalogue « IA et productivité » + CFA commerce et vente : être référencé comme intervenant | J7: A | K7: À contacter | M7: https://reunion.cci.fr/se-former/ecolescentres-de-formations/liste-des-nos-ecoles-cfa
A8: CFA Disciplina | B8: Réunion | C8: CFA | D8: Vente | I8: Cherchait des formateurs vente indépendants | J8: A | K8: À contacter | M8: https://candidat.francetravail.fr/offres/emploi/formateur/reunion/s20m22d974
A9: IFR – Institut de Formation de la Réunion | B9: Réunion | C9: OF 974 | D9: IA pour tous, commerce, informatique, communication digitale | H9: https://www.ifr-reunion.re/formation-ia-pour-tous/ | I9: Module « IA + RGPD » en complément de « IA pour tous » | J9: A | K9: À contacter | M9: https://www.ifr-reunion.re/formation-ia-pour-tous/
A10: JD Formations | B10: Réunion | C10: OF 974 | D10: IA (ChatGPT), métiers | H10: https://www.jdformations.re/formation-ia-chatgpt-a-la-reunion-974/ | I10: Formation IA par métier : proposez co-animation et module conformité | J10: A | K10: À contacter | M10: https://www.jdformations.re/formation-ia-chatgpt-a-la-reunion-974/
A11: Numeria | B11: Réunion | C11: OF 974 | D11: IA, numérique | H11: https://www.numeria-formation.re/formations-intelligence-artificielle/ | I11: Organise des formations IA : proposez le volet RGPD / IA Act et du renfort de formateurs | J11: A | K11: À contacter | M11: https://www.numeria-formation.re/formations-intelligence-artificielle/
A12: Réunion Prospectives Compétences (Carif-Oref) | B12: Réunion | C12: Prescripteur public | D12: Information sur la formation (formanoo.org) | F12: 02 62 83 00 40 | G12: contact@rpc.re | H12: https://www.rpc.re | I12: Faites référencer vos formations sur formanoo.org : visibilité auprès des prescripteurs | J12: A | K12: À contacter | M12: https://centre-inffo.fr/content/uploads/2024/06/depliant-reseaux-062024.pdf
A13: Sarl Laboratoire L & M | B13: Réunion | C13: OF 974 | D13: Management, comptabilité, numérique / cybersécurité, bureautique, vente (+ pâtisserie, HACCP) | I13: A publié des offres de formateurs en management, numérique et techniques de vente | J13: A | K13: À contacter | M13: https://candidat.francetravail.fr/offres/emploi/formateur/reunion/s20m22d974
A14: DCP Formation | B14: Réunion – Le Tampon + Mayotte | C14: Réseau national, centres locaux | D14: Informatique, IA, management, RH, comptabilité | E14: 4 rue du Collège, Plaine des Cafres, 97418 Le Tampon (+ centre à Mamoudzou) | H14: https://dcpformation.fr/centre_de_formation/letampon-974/ | I14: Affiche l'IA et le management, et un centre à Mayotte : 2 territoires possibles | J14: A | K14: À contacter | M14: https://dcpformation.fr/centre_de_formation/letampon-974/
A15: Digitalys | B15: Réunion – Saint-André | C15: OF 974 | D15: Soft skills, numérique | E15: 825 avenue des Mascareignes, 97440 Saint-André | F15: 02 62 73 83 52 | G15: contact@digitalysformation.fr | I15: Soft skills + numérique : votre double profil | J15: A | K15: À contacter | M15: https://www.capitecorpus.com/formation-communication-soft-skills/
A16: AKADEMIA FORMATION | B16: Réunion – Saint-Denis | C16: OF 974 | D16: IA | E16: Saint-Denis 97400 | I16: Annonce « formateur indépendant – Initiation à l'IA » (7 h, présentiel) : candidatez si elle est encore en ligne | J16: A | K16: À contacter | M16: https://fr.indeed.com/q-formateur-ia-l-la-r%C3%A9union-emplois.html
A17: CQFD Pro | B17: Réunion – Saint-Denis | C17: OF 974 | D17: Formation continue sur mesure en entreprise | E17: Saint-Denis | I17: Formation sur mesure en entreprise : votre cœur de métier (vente, management, IA) | J17: A | K17: À contacter | M17: https://www.pagesjaunes.fr/annuaire/saint-denis-974/organisme-de-formation
A18: GRETA Réunion (antenne Nord) | B18: Réunion – Saint-Denis | C18: Public (Éducation nationale) | D18: IA générative (RS 6776), tous domaines | E18: Saint-Denis | H18: https://ftlvreunion.fr/en-ce-moment/news/formation-ia-generative-en-presentiel.html | I18: Sessions IA du 16 au 18/11/2026 : vacations, module éthique et conformité | J18: A | K18: À contacter | M18: https://ftlvreunion.fr/en-ce-moment/news/formation-ia-generative-en-presentiel.html
A19: Educatis Forma | B19: Réunion – Saint-Paul | C19: OF 974 | D19: Négociation commerciale, assistanat | E19: Saint-Paul | I19: Recrutait des formateurs en négociation commerciale | J19: A | K19: À contacter | M19: https://candidat.francetravail.fr/offres/emploi/formateur/reunion/s20m22d974
A20: Axam Formation | B20: Réunion – Saint-Pierre | C20: Réseau national | D20: Informatique, bureautique, Power BI | E20: Saint-Pierre 974 | H20: https://www.axamformation.fr/informatique-saint-pierre/974 | I20: Ajoutez l'IA à leur catalogue bureautique (Copilot, Gemini) | J20: A | K20: À contacter | M20: https://www.axamformation.fr/informatique-saint-pierre/974
A21: Agepac Formation | B21: Réunion – Sainte-Clotilde | C21: CFA / OF (Qualiopi) | D21: BTS MCO, GPME, assurance | E21: Sainte-Clotilde, 97490 Saint-Denis | H21: https://www.wizbii.com/company/agepac | I21: BTS MCO = management commercial : vente, management, IA | J21: A | K21: À contacter | M21: https://www.wizbii.com/company/agepac/job/assistant-commercial-gestion-et-relation-client-pro-pme-h-f-bts-mco-en-alternance-age13562
A22: Appavoo Business School | B22: Maurice | C22: Organisme agréé MQA | D22: Formation en entreprise | H22: https://appavoo.com/education-n-training/ | I22: Partenariat IA + vente / management | J22: B | K22: À contacter | M22: https://appavoo.com/education-n-training/
A23: IT Academy | B23: Maurice – Port-Louis | C23: Centre agréé MQA | D23: Certifications informatiques | E23: Port-Louis | H23: https://www.facebook.com/itacademy.mu/ | I23: Module IA appliquée | J23: B | K23: À contacter | M23: https://www.facebook.com/itacademy.mu/
A24: ESCGM – École supérieure de commerce et de gestion de Mayotte | B24: Mayotte | C24: École / OF | D24: Informatique, développeur web, commerce | I24: IA et RGPD dans les cursus informatique et commerce | J24: B | K24: À contacter | M24: https://www.intercariforef.org/formations/cole-suprieur-de-commerce-et-de-gestion-de-mayotte.-escgm/organisme-39_225.html
A25: ITG Learning | B25: Métropole → 974 | C25: OF qui porte des formateurs indépendants | D25: IA, tous domaines | I25: Déjà utilisé par un formateur IA du 974 pour la prise en charge OPCO. Vous avez votre propre Qualiopi : proposez-leur l'inverse, des missions en sous-traitance | J25: B | K25: À contacter | M25: https://jmberthelot.com/formation-intelligence-artificielle-la-reunion.html
A26: CNFPT – délégation Réunion | B26: Réunion | C26: Public (agents territoriaux) | D26: Formation des collectivités | H26: https://www.cnfpt.fr/se-former/suivre-formation/inscription-ligne/vos-interlocuteurs-formation-a-delegation-reunion/vos-contacts-a-delegation-reunion/reunion | I26: Les collectivités se forment à l'IA : se faire référencer comme intervenant | J26: B | K26: À contacter | M26: https://www.cnfpt.fr/se-former/suivre-formation/inscription-ligne/vos-interlocuteurs-formation-a-delegation-reunion/vos-contacts-a-delegation-reunion/reunion
A27: Simplon (partenaire de l'AFPAR) | B27: Réunion | C27: OF national | D27: Développeur IA | I27: Module conformité IA Act / RGPD dans la formation développeur IA | J27: B | K27: À contacter | M27: https://outremers360.com/bassin-indien-appli/la-reunion-une-premiere-formation-de-developpeur-en-intelligence-artificielle-pour-le-territoire
A28: AFPAR | B28: Réunion (4 centres) | C28: Organisme régional | D28: 150 formations, parcours développeur IA | E28: Centres de Saint-André, Saint-Denis, Saint-Paul, Saint-Pierre | H28: https://afpar.re/ | I28: Intervenant « éthique, RGPD, IA Act » dans le parcours IA | J28: B | K28: À contacter | M28: https://afpar.re/
A29: Envergure | B29: Réunion – La Possession | C29: OF 974 (Qualiopi) | D29: Accompagnement de consultants indépendants | E29: 5 rue Justin Baptiste, 97419 La Possession | I29: Travaille avec des consultants indépendants : partenariat naturel | J29: B | K29: À contacter | M29: https://www.pagesjaunes.fr/annuaire/le-port-974/organisme-de-formation
A30: ILOI – Institut de l'Image de l'Océan Indien | B30: Réunion – Le Port | C30: École | D30: Audiovisuel, création numérique, IA | E30: Le Port | I30: Recrutait des formateurs externes 2026-2027 avec un module IA (clos le 24/09) : candidature spontanée | J30: B | K30: À contacter | M30: Résultat de recherche e-marchespublics.com
A31: CFA Horizon Réunion | B31: Réunion – Le Tampon | C31: CFA (Qualiopi) | D31: Vente, commerce, marketing (Bac à Bac+3) | E31: 4 boulevard Michel Debré, 97430 Le Tampon | I31: Vente + IA appliquée au commerce | J31: B | K31: À contacter | M31: https://www.pagesjaunes.fr/pros/12005556
A32: Form'aou | B32: Réunion – Saint-André + Saint-Louis | C32: OF / CFA | D32: Commerce, administration, coiffure | E32: Saint-André (+ centre à Saint-Louis) | I32: Commerce et vente | J32: B | K32: À contacter | M32: https://candidat.francetravail.fr/offres/emploi/formateur/reunion/s20m22d974
A33: Advance Formation & Développement | B33: Réunion – Saint-Benoît | C33: OF 974 | D33: Soft skills | E33: Saint-Benoît | H33: https://www.mesenseignes.fr/advance-formation-developpement/5167-formation-soft-skills-a-lile-de-la-reunion-974/ | I33: Soft skills : votre expertise historique | J33: B | K33: À contacter | M33: https://www.mesenseignes.fr/advance-formation-developpement/5167-formation-soft-skills-a-lile-de-la-reunion-974/
A34: Run Paye Formation | B34: Réunion – Saint-Benoît | C34: OF 974 | D34: Paie, gestion | E34: 55 rue Auguste de Villèle, 97470 Saint-Benoît | I34: IA et RGPD pour les gestionnaires de paie (données sensibles) | J34: B | K34: À contacter | M34: https://www.pagesjaunes.fr/annuaire/saint-benoit-974/formation-professionnelle
A35: CFA de l'Université de La Réunion / FTLV | B35: Réunion – Saint-Denis | C35: Public (université) | D35: Tertiaire, numérique | E35: 2 rue Joseph Wetzell, 97400 Saint-Denis | H35: https://ftlvreunion.fr/ | I35: Intervenant professionnel IA / RGPD en licence pro et formation continue | J35: B | K35: À contacter | M35: http://geolocalisation.onisep.fr/974-la-reunion/saint-denis/cfa/centre-de-formation-d-apprentis-de-l-universite-de-la-reunion-universite-de-la-reunion.html
A36: EAFC – École académique de la formation continue | B36: Réunion – Saint-Denis | C36: Public (académie) | D36: Formation continue | E36: 24 avenue Georges Brassens, 97400 Saint-Denis | F36: 02 62 48 13 39 | I36: Recrute des intervenants vacataires : dossier de candidature | J36: B | K36: À contacter | M36: https://www.ac-reunion.fr/media/46832/download
A37: Develop'A Ou | B37: Réunion – Saint-Leu | C37: OF 974 (Qualiopi) | D37: Bureautique, informatique, accueil, petite enfance | E37: 5 chemin des Francisceas, 97425 Saint-Leu | I37: IA dans les formations bureautique | J37: B | K37: À contacter | M37: https://www.pagesjaunes.fr/annuaire/saint-leu-974/apprentissage-formation-professionnelle
A38: Ariane Formation | B38: Réunion – Saint-Paul | C38: OF 974 (Qualiopi depuis 2003) | D38: Formation continue | E38: 6 route de Savanna, 97460 Saint-Paul | H38: https://www.ariane-formation.re/ | I38: Candidature spontanée | J38: B | K38: À contacter | M38: https://www.ariane-formation.re/
A39: Capital Formation | B39: Réunion – Saint-Paul | C39: OF 974 (Qualiopi, 20 ans) | D39: Formation continue, bilan, apprentissage | E39: 171 Chaussée Royale, 1er étage, 97460 Saint-Paul | I39: Candidature : management, vente, IA | J39: B | K39: À contacter | M39: https://www.pagesjaunes.fr/annuaire/saint-paul-974/formation-professionnelle
A40: AREFIP | B40: Réunion – Saint-Pierre | C40: OF 974 (Qualiopi depuis l'origine) | D40: Formation professionnelle, informatique, solutions RH | E40: 24 Cité de la Plaine, 97410 Saint-Pierre | F40: 02 62 96 19 79 | H40: https://www.arefip.fr/ | I40: Informatique + RH : IA et RGPD pour les fonctions RH | J40: B | K40: À contacter | M40: https://www.arefip.fr/
A41: CEFOR – Centre d'enseignement et de formation de la Réunion | B41: Réunion – Saint-Pierre | C41: CFA | D41: BTS comptabilité et gestion | E41: 2 avenue Laurent Vergès, 97432 Saint-Pierre | I41: IA pour la comptabilité et la gestion | J41: B | K41: À contacter | M41: https://dossierappel.parcoursup.fr/Candidats/public/fiches/afficherFicheFormation?g_ta_cod=48130&typeBac=0&originePc=0
A42: GEM Formation | B42: Réunion – Saint-Pierre | C42: OF / CFA (Qualiopi) | D42: Assistant de direction, formation continue, bilan, VAE | E42: 35 ter rue du Four à Chaux, 97410 Saint-Pierre | H42: https://www.facebook.com/gemformation974/ | I42: 10 à 19 salariés ; modules IA bureautique pour assistants de direction | J42: B | K42: À contacter | M42: https://www.pagesjaunes.fr/annuaire/saint-pierre-974/formation-professionnelle
A43: Success Formation | B43: Réunion – Saint-Pierre | C43: CFA / OF | D43: Assistant manager, assistant commercial, logistique | E43: Saint-Pierre | I43: Titres « assistant manager » et « commercial » : management et vente | J43: B | K43: À contacter | M43: https://candidat.francetravail.fr/offres/emploi/formateur/reunion/s20m22d974
A44: Unicomp Computer Training Institute | B44: Maurice – Port-Louis | C44: Organisme agréé MQA | D44: Informatique | E44: St Pierre, Port-Louis | H44: https://unicomp.mu/ | I44: Module IA appliquée | J44: C | K44: À contacter | M44: https://unicomp.mu/
A45: Forma Plus Consulting | B45: Mayotte | C45: OF 976 (Qualiopi) | D45: Formation professionnelle | I45: Candidature spontanée | J45: C | K45: À contacter | M45: https://www.pagesjaunes.fr/annuaire/departement/mayotte-976/formation-professionnelle
A46: CFPEI | B46: Mayotte – Mamoudzou | C46: OF 976 | D46: Emploi et insertion | E46: Mamoudzou | I46: Candidature spontanée | J46: C | K46: À contacter | M46: https://www.pagesjaunes.fr/annuaire/departement/mayotte-976/formation-professionnelle
A47: Forma Boost | B47: Mayotte – Mamoudzou | C47: OF 976 | D47: Formation professionnelle | E47: Mamoudzou | I47: Candidature spontanée | J47: C | K47: À contacter | M47: https://www.pagesjaunes.fr/pros/61699180
A48: Mayotte Consulting et Formation | B48: Mayotte – Mamoudzou | C48: OF 976 | D48: Formation continue | E48: 18 rue Zamantale, Kawéni, 97600 Mamoudzou | I48: Candidature spontanée | J48: C | K48: À contacter | M48: https://www.pagesjaunes.fr/pros/55055224
A49: Boomerang Océan Indien | B49: Réunion | C49: Réseau d'insertion | D49: Confiance, stress, travail en équipe, codes de l'entreprise | H49: https://boomerang-oi.fr/ | I49: Insertion + soft skills ; votre casquette de référent handicap compte | J49: C | K49: À contacter | M49: https://boomerang-oi.fr/
A50: ERFP – École régionale de la formation professionnelle | B50: Réunion | C50: OF 974 | D50: Apprentissage, formation continue | I50: Candidature spontanée | J50: C | K50: À contacter | M50: https://www.pagesjaunes.fr/annuaire/saint-denis-974/organisme-de-formation
A51: ISFOI | B51: Réunion | C51: OF 974 | D51: Formation professionnelle | I51: Candidature spontanée | J51: C | K51: À contacter | M51: Résultat de recherche Indeed
A52: Inclus à Nous | B52: Réunion | C52: OF 974 | D52: Soft skills en groupes | H52: https://www.inclusanous.re/groupes.html | I52: Soft skills, groupes de 10-12 personnes | J52: C | K52: À contacter | M52: https://www.inclusanous.re/groupes.html
A53: Eximus Formation | B53: Réunion – Est | C53: OF 974 (Qualiopi) | D53: Formation continue | I53: Candidature spontanée | J53: C | K53: À contacter | M53: https://www.pagesjaunes.fr/annuaire/saint-andre-974/formation-professionnelle
A54: Cap Formation | B54: Réunion – Le Port | C54: OF 974 (Qualiopi) | D54: Formation continue | E54: 4 rue François de Mahy, 97420 Le Port | H54: https://www.pagesjaunes.fr/pros/07769038 | I54: Candidature spontanée | J54: C | K54: À contacter | M54: https://www.pagesjaunes.fr/pros/07769038
A55: ABC Formation Continue | B55: Réunion – Saint-Denis | C55: OF 974 | D55: Formation continue | E55: Saint-Denis 97400 | H55: https://www.maformation.fr/centres/marque_abc-formation-continue_ville_saint-denis-97400.html | I55: Candidature spontanée | J55: C | K55: À contacter | M55: https://www.maformation.fr/centres/marque_abc-formation-continue_ville_saint-denis-97400.html
A56: CFOR – Centre de formation Ouest Réunion | B56: Réunion – Saint-Paul | C56: OF 974 (Qualiopi) | D56: Présentiel et distanciel | E56: 11 rue Hôpital, 97460 Saint-Paul | I56: Candidature spontanée | J56: C | K56: À contacter | M56: https://www.pagesjaunes.fr/annuaire/saint-paul-974/formation-professionnelle
A57: Arena Run | B57: Réunion – Saint-Pierre | C57: OF 974 | D57: Formation continue | E57: 132 rue Victor le Vigoureux, 97410 Saint-Pierre | I57: Candidature spontanée | J57: C | K57: À contacter | M57: https://fr.mappy.com/poi/589bb27b0351d167ec4d43a6
A58: FRIC Formation | B58: Réunion – Saint-Pierre | C58: OF 974 (Qualiopi) | D58: Formation continue | E58: 70 rue Suffren, 97410 Saint-Pierre | F58: 06 93 20 69 00 | I58: Candidature spontanée | J58: C | K58: À contacter | M58: https://www.pagesjaunes.fr/annuaire/saint-pierre-974/formation-professionnelle
A59: Réussir SARL | B59: Réunion – Saint-Pierre | C59: OF 974 | D59: Formation continue | E59: 10 bis chemin Maxime Rivière, 97410 Saint-Pierre | I59: Candidature spontanée | J59: C | K59: À contacter | M59: https://fr.mappy.com/poi/589c0f910351d167ec4d6a74
A60: SARL CAP'R HQS | B60: Réunion – Saint-Pierre | C60: OF 974 (Qualiopi) | D60: Formation continue | E60: 43B rue du Presbytère, 97410 Saint-Pierre | F60: 06 92 17 50 02 | I60: Candidature spontanée | J60: C | K60: À contacter | M60: https://www.pagesjaunes.fr/annuaire/saint-pierre-974/formation-professionnelle

Sheet Synthèse
A1: Tableau de bord prospection (se met à jour quand vous changez les statuts)
A3: Secteur | B3: Priorité | C3: Nb entreprises | D3: Avec téléphone | E3: Contactés | F3: RDV | G3: Clients | H3: Oppositions
A4: Cabinets d'avocats | B4: 1 | C4: =COUNTIF('Prospects 974'!$C$2:$C$107,A4) | D4: =COUNTIFS('Prospects 974'!$C$2:$C$107,A4,'Prospects 974'!$G$2:$G$107,"<>") | E4: =COUNTIFS('Prospects 974'!$C$2:$C$107,A4,'Prospects 974'!$L$2:$L$107,"Contacté")+G4+F4+COUNTIFS('Prospects 974'!$C$2:$C$107,A4,'Prospects 974'!$L$2:$L$107,"Proposition") | F4: =COUNTIFS('Prospects 974'!$C$2:$C$107,A4,'Prospects 974'!$L$2:$L$107,"RDV") | G4: =COUNTIFS('Prospects 974'!$C$2:$C$107,A4,'Prospects 974'!$L$2:$L$107,"Client") | H4: =COUNTIFS('Prospects 974'!$C$2:$C$107,A4,'Prospects 974'!$L$2:$L$107,"Opposition RGPD")
A5: Courtage & assurance | B5: 1 | C5: =COUNTIF('Prospects 974'!$C$2:$C$107,A5) | D5: =COUNTIFS('Prospects 974'!$C$2:$C$107,A5,'Prospects 974'!$G$2:$G$107,"<>") | E5: =COUNTIFS('Prospects 974'!$C$2:$C$107,A5,'Prospects 974'!$L$2:$L$107,"Contacté")+G5+F5+COUNTIFS('Prospects 974'!$C$2:$C$107,A5,'Prospects 974'!$L$2:$L$107,"Proposition") | F5: =COUNTIFS('Prospects 974'!$C$2:$C$107,A5,'Prospects 974'!$L$2:$L$107,"RDV") | G5: =COUNTIFS('Prospects 974'!$C$2:$C$107,A5,'Prospects 974'!$L$2:$L$107,"Client") | H5: =COUNTIFS('Prospects 974'!$C$2:$C$107,A5,'Prospects 974'!$L$2:$L$107,"Opposition RGPD")
A6: Expertise comptable | B6: 1 | C6: =COUNTIF('Prospects 974'!$C$2:$C$107,A6) | D6: =COUNTIFS('Prospects 974'!$C$2:$C$107,A6,'Prospects 974'!$G$2:$G$107,"<>") | E6: =COUNTIFS('Prospects 974'!$C$2:$C$107,A6,'Prospects 974'!$L$2:$L$107,"Contacté")+G6+F6+COUNTIFS('Prospects 974'!$C$2:$C$107,A6,'Prospects 974'!$L$2:$L$107,"Proposition") | F6: =COUNTIFS('Prospects 974'!$C$2:$C$107,A6,'Prospects 974'!$L$2:$L$107,"RDV") | G6: =COUNTIFS('Prospects 974'!$C$2:$C$107,A6,'Prospects 974'!$L$2:$L$107,"Client") | H6: =COUNTIFS('Prospects 974'!$C$2:$C$107,A6,'Prospects 974'!$L$2:$L$107,"Opposition RGPD")
A7: Immobilier | B7: 1 | C7: =COUNTIF('Prospects 974'!$C$2:$C$107,A7) | D7: =COUNTIFS('Prospects 974'!$C$2:$C$107,A7,'Prospects 974'!$G$2:$G$107,"<>") | E7: =COUNTIFS('Prospects 974'!$C$2:$C$107,A7,'Prospects 974'!$L$2:$L$107,"Contacté")+G7+F7+COUNTIFS('Prospects 974'!$C$2:$C$107,A7,'Prospects 974'!$L$2:$L$107,"Proposition") | F7: =COUNTIFS('Prospects 974'!$C$2:$C$107,A7,'Prospects 974'!$L$2:$L$107,"RDV") | G7: =COUNTIFS('Prospects 974'!$C$2:$C$107,A7,'Prospects 974'!$L$2:$L$107,"Client") | H7: =COUNTIFS('Prospects 974'!$C$2:$C$107,A7,'Prospects 974'!$L$2:$L$107,"Opposition RGPD")
A8: Notariat | B8: 1 | C8: =COUNTIF('Prospects 974'!$C$2:$C$107,A8) | D8: =COUNTIFS('Prospects 974'!$C$2:$C$107,A8,'Prospects 974'!$G$2:$G$107,"<>") | E8: =COUNTIFS('Prospects 974'!$C$2:$C$107,A8,'Prospects 974'!$L$2:$L$107,"Contacté")+G8+F8+COUNTIFS('Prospects 974'!$C$2:$C$107,A8,'Prospects 974'!$L$2:$L$107,"Proposition") | F8: =COUNTIFS('Prospects 974'!$C$2:$C$107,A8,'Prospects 974'!$L$2:$L$107,"RDV") | G8: =COUNTIFS('Prospects 974'!$C$2:$C$107,A8,'Prospects 974'!$L$2:$L$107,"Client") | H8: =COUNTIFS('Prospects 974'!$C$2:$C$107,A8,'Prospects 974'!$L$2:$L$107,"Opposition RGPD")
A9: Commerce de gros | B9: 2 | C9: =COUNTIF('Prospects 974'!$C$2:$C$107,A9) | D9: =COUNTIFS('Prospects 974'!$C$2:$C$107,A9,'Prospects 974'!$G$2:$G$107,"<>") | E9: =COUNTIFS('Prospects 974'!$C$2:$C$107,A9,'Prospects 974'!$L$2:$L$107,"Contacté")+G9+F9+COUNTIFS('Prospects 974'!$C$2:$C$107,A9,'Prospects 974'!$L$2:$L$107,"Proposition") | F9: =COUNTIFS('Prospects 974'!$C$2:$C$107,A9,'Prospects 974'!$L$2:$L$107,"RDV") | G9: =COUNTIFS('Prospects 974'!$C$2:$C$107,A9,'Prospects 974'!$L$2:$L$107,"Client") | H9: =COUNTIFS('Prospects 974'!$C$2:$C$107,A9,'Prospects 974'!$L$2:$L$107,"Opposition RGPD")
A10: Informatique / ESN | B10: 2 | C10: =COUNTIF('Prospects 974'!$C$2:$C$107,A10) | D10: =COUNTIFS('Prospects 974'!$C$2:$C$107,A10,'Prospects 974'!$G$2:$G$107,"<>") | E10: =COUNTIFS('Prospects 974'!$C$2:$C$107,A10,'Prospects 974'!$L$2:$L$107,"Contacté")+G10+F10+COUNTIFS('Prospects 974'!$C$2:$C$107,A10,'Prospects 974'!$L$2:$L$107,"Proposition") | F10: =COUNTIFS('Prospects 974'!$C$2:$C$107,A10,'Prospects 974'!$L$2:$L$107,"RDV") | G10: =COUNTIFS('Prospects 974'!$C$2:$C$107,A10,'Prospects 974'!$L$2:$L$107,"Client") | H10: =COUNTIFS('Prospects 974'!$C$2:$C$107,A10,'Prospects 974'!$L$2:$L$107,"Opposition RGPD")
A11: Intérim & recrutement | B11: 2 | C11: =COUNTIF('Prospects 974'!$C$2:$C$107,A11) | D11: =COUNTIFS('Prospects 974'!$C$2:$C$107,A11,'Prospects 974'!$G$2:$G$107,"<>") | E11: =COUNTIFS('Prospects 974'!$C$2:$C$107,A11,'Prospects 974'!$L$2:$L$107,"Contacté")+G11+F11+COUNTIFS('Prospects 974'!$C$2:$C$107,A11,'Prospects 974'!$L$2:$L$107,"Proposition") | F11: =COUNTIFS('Prospects 974'!$C$2:$C$107,A11,'Prospects 974'!$L$2:$L$107,"RDV") | G11: =COUNTIFS('Prospects 974'!$C$2:$C$107,A11,'Prospects 974'!$L$2:$L$107,"Client") | H11: =COUNTIFS('Prospects 974'!$C$2:$C$107,A11,'Prospects 974'!$L$2:$L$107,"Opposition RGPD")
A12: Transport & logistique | B12: 2 | C12: =COUNTIF('Prospects 974'!$C$2:$C$107,A12) | D12: =COUNTIFS('Prospects 974'!$C$2:$C$107,A12,'Prospects 974'!$G$2:$G$107,"<>") | E12: =COUNTIFS('Prospects 974'!$C$2:$C$107,A12,'Prospects 974'!$L$2:$L$107,"Contacté")+G12+F12+COUNTIFS('Prospects 974'!$C$2:$C$107,A12,'Prospects 974'!$L$2:$L$107,"Proposition") | F12: =COUNTIFS('Prospects 974'!$C$2:$C$107,A12,'Prospects 974'!$L$2:$L$107,"RDV") | G12: =COUNTIFS('Prospects 974'!$C$2:$C$107,A12,'Prospects 974'!$L$2:$L$107,"Client") | H12: =COUNTIFS('Prospects 974'!$C$2:$C$107,A12,'Prospects 974'!$L$2:$L$107,"Opposition RGPD")
A13: Agences de voyages | B13: 3 | C13: =COUNTIF('Prospects 974'!$C$2:$C$107,A13) | D13: =COUNTIFS('Prospects 974'!$C$2:$C$107,A13,'Prospects 974'!$G$2:$G$107,"<>") | E13: =COUNTIFS('Prospects 974'!$C$2:$C$107,A13,'Prospects 974'!$L$2:$L$107,"Contacté")+G13+F13+COUNTIFS('Prospects 974'!$C$2:$C$107,A13,'Prospects 974'!$L$2:$L$107,"Proposition") | F13: =COUNTIFS('Prospects 974'!$C$2:$C$107,A13,'Prospects 974'!$L$2:$L$107,"RDV") | G13: =COUNTIFS('Prospects 974'!$C$2:$C$107,A13,'Prospects 974'!$L$2:$L$107,"Client") | H13: =COUNTIFS('Prospects 974'!$C$2:$C$107,A13,'Prospects 974'!$L$2:$L$107,"Opposition RGPD")
A14: Automobile | B14: 3 | C14: =COUNTIF('Prospects 974'!$C$2:$C$107,A14) | D14: =COUNTIFS('Prospects 974'!$C$2:$C$107,A14,'Prospects 974'!$G$2:$G$107,"<>") | E14: =COUNTIFS('Prospects 974'!$C$2:$C$107,A14,'Prospects 974'!$L$2:$L$107,"Contacté")+G14+F14+COUNTIFS('Prospects 974'!$C$2:$C$107,A14,'Prospects 974'!$L$2:$L$107,"Proposition") | F14: =COUNTIFS('Prospects 974'!$C$2:$C$107,A14,'Prospects 974'!$L$2:$L$107,"RDV") | G14: =COUNTIFS('Prospects 974'!$C$2:$C$107,A14,'Prospects 974'!$L$2:$L$107,"Client") | H14: =COUNTIFS('Prospects 974'!$C$2:$C$107,A14,'Prospects 974'!$L$2:$L$107,"Opposition RGPD")
A15: Hôtellerie | B15: 3 | C15: =COUNTIF('Prospects 974'!$C$2:$C$107,A15) | D15: =COUNTIFS('Prospects 974'!$C$2:$C$107,A15,'Prospects 974'!$G$2:$G$107,"<>") | E15: =COUNTIFS('Prospects 974'!$C$2:$C$107,A15,'Prospects 974'!$L$2:$L$107,"Contacté")+G15+F15+COUNTIFS('Prospects 974'!$C$2:$C$107,A15,'Prospects 974'!$L$2:$L$107,"Proposition") | F15: =COUNTIFS('Prospects 974'!$C$2:$C$107,A15,'Prospects 974'!$L$2:$L$107,"RDV") | G15: =COUNTIFS('Prospects 974'!$C$2:$C$107,A15,'Prospects 974'!$L$2:$L$107,"Client") | H15: =COUNTIFS('Prospects 974'!$C$2:$C$107,A15,'Prospects 974'!$L$2:$L$107,"Opposition RGPD")
... A17: BTP | B17: 4 | C17: =COUNTIF('Prospects 974'!$C$2:$C$107,A17) | D17: =COUNTIFS('Prospects 974'!$C$2:$C$107,A17,'Prospects 974'!$G$2:$G$107,"<>") | E17: =COUNTIFS('Prospects 974'!$C$2:$C$107,A17,'Prospects 974'!$L$2:$L$107,"Contacté")+G17+F17+COUNTIFS('Prospects 974'!$C$2:$C$107,A17,'Prospects 974'!$L$2:$L$107,"Proposition") | F17: =COUNTIFS('Prospects 974'!$C$2:$C$107,A17,'Prospects 974'!$L$2:$L$107,"RDV") | G17: =COUNTIFS('Prospects 974'!$C$2:$C$107,A17,'Prospects 974'!$L$2:$L$107,"Client") | H17: =COUNTIFS('Prospects 974'!$C$2:$C$107,A17,'Prospects 974'!$L$2:$L$107,"Opposition RGPD")
A18: TOTAL | C18: =SUM(C4:C17) | D18: =SUM(D4:D17) | E18: =SUM(E4:E17) | F18: =SUM(F4:F17) | G18: =SUM(G4:G17) | H18: =SUM(H4:H17)
A20: « Contactés » = Contacté + Proposition + RDV + Client (toute entreprise déjà touchée).
