Workbook

Sheet Mode d'emploi
A1: PROSPECTION — ACTEURS DE LA FORMATION À LA RÉUNION
A2: Version | B2: 22 octobre 2026 — YEBA FORMATIONS (usage interne)
A4: Onglets | B4: Acteurs (coordonnées, décideurs, accroches) · Missions longues · Chiffrage · OPCO · Preuves
A5: Cellules à remplir | B5: Fond jaune : Statut, Prochain contact, Notes (onglet Acteurs) et Tarif journalier (onglet Chiffrage).
A6: [À VÉRIFIER] | B6: Information non confirmée par une source récente : appelez le standard avant de l'utiliser. Ne citez jamais une information [À VÉRIFIER] en rendez-vous.
A7: Accroches | B7: Remplacez les « … » par deux dates précises. Une accroche ne contraint personne à dire oui : elle obtient un rendez-vous. Un acheteur public ne peut pas vous commander une mission au-dessus de 60 000 € HT sans procédure de mise en concurrence.
A8: Ligne verte | B8: Priorité 1 = à contacter en premier.
A10: RGPD — ce fichier | B10: Les noms de décideurs sont des données personnelles, issues de sources publiques et limitées à la fonction professionnelle. Base légale : intérêt légitime (prospection B2B en lien avec la fonction). Conservation : 3 ans après le dernier contact. Ne stockez pas ce fichier hors UE (Baserow cloud UE ou disque local chiffré).
A11: RGPD — mention à coller sous votre 1er email (art. 14) | B11: « Vos coordonnées professionnelles proviennent de sources publiques (presse, sites institutionnels). Elles sont traitées par YEBA FORMATIONS, sur la base de son intérêt légitime, pour vous présenter son offre de formation, et conservées 3 ans après notre dernier échange. Vous pouvez vous y opposer à tout moment en répondant « STOP », et exercer vos droits d'accès, de rectification et d'effacement à [votre adresse email]. Vous pouvez aussi saisir la CNIL (cnil.fr). »
A12: IA Act — à jour | B12: Omnibus (règlement UE 2026/1744, en vigueur le 27/07/2026) : l'art. 4 impose désormais de prendre des mesures de maîtrise de l'IA (plus un « niveau suffisant » garanti) ; haut risque annexe III reporté au 02/12/2027 ; art. 50 (transparence) applicable depuis le 02/08/2026. Vérifiez le texte sur EUR-Lex avant de le citer à un client.

Sheet Acteurs
A1: N° | B1: Priorité | C1: Acteur | D1: Catégorie | E1: OPCO / financeur à mobiliser | F1: Décideur identifié | G1: Fonction | H1: Fiabilité du nom (source, date) | I1: Service / porte d'entrée | J1: Adresse | K1: Téléphone | L1: Email / site | M1: Douleur n°1 (preuve chiffrée) | N1: Accroche prête à l'emploi (email / 1er appel) | O1: Objection probable → votre réponse | P1: Offre à proposer | Q1: Mission longue (onglet) | R1: Voie d'achat / financement | S1: RGPD | T1: IA Act | U1: Statut | V1: Prochain contact (date) | W1: Notes | X1: Sources
A2: 1 | B2: 1 | C2: Région Réunion | D2: Financeur public | E2: Région (PRF, AF2R) + FSE+ ; Contrat de Filière Numérique | F2: Karine NABENESA (Huguette BELLO, Présidente) | G2: 4e Vice-présidente déléguée à la formation professionnelle et à l'apprentissage | H2: Monographie Centre Inffo, déc. 2025 — à reconfirmer | I2: Direction de la formation professionnelle (réf. marchés « DFP ») + service pilote du Contrat de Filière Numérique [À VÉRIFIER] | J2: Hôtel de Région Pierre Lagourgue, avenue René Cassin, Moufia, 97490 Sainte-Clotilde — Courrier : BP 7190, 97719 Saint-Denis Cedex 9 | K2: 02 62 48 70 00 (standard, avis 2012) [À VÉRIFIER] | L2: marches@cr-reunion.fr (avis 2017) [À VÉRIFIER] — regionreunion.com | M2: Dépenses formation 70,3 M€ (2022) → 113,8 M€ (2024), mais chômage remonté à 19 % au T2 2026. Objectif signé le 18/02/2026 : transformer numériquement 8 000 TPE-PME d'ici 2028. Marchés PRF 2026 jugés d'abord sur le prix (volet 3 : 22 lots). | N2: Madame la Vice-présidente, Le 18 février, la Région a signé un Contrat de Filière Numérique qui engage la transformation de 8 000 TPE-PME d'ici 2028. Dans le même temps, le chômage est remonté à 19 % au 2e trimestre. Le défi n'est plus de financer des heures : c'est de prouver des résultats. Je vous propose un programme de 24 mois qui forme les dirigeants et salariés de TPE-PME à une IA utile ET conforme (RGPD, IA Act), avec des supports accessibles aux personnes malvoyantes et un indicateur simple : chaque stagiaire repart avec un cas d'usage IA en production dans son entreprise et son registre RGPD simplifié. Organisme Qualiopi, Référent handicap, formé par l'ANSSI et la CNIL, certifié Google AI : je suis aujourd'hui l'un des rares sur l'île à réunir IA, conformité et accessibilité. Puis-je vous présenter ce programme en 20 minutes, la semaine du … ou celle du … ? Aurélien LUMEKA — Directeur, YEBA FORMATIONS (Qualiopi 25FOR02027.1 — NDA 04973676397) | O2: « Nous achetons par marchés publics (PRF) » → « Justement : je ne vous demande aucune commande aujourd'hui. Le Code de la commande publique (art. R2111-1) vous autorise à consulter des entreprises en amont : 20 minutes de sourcing pour que le prochain volet intègre un lot « IA & conformité ». Sur un gros lot, je candidaterai en groupement. » | P2: Programme « IA utile & conforme — TPE-PME 974 » + formation des agents régionaux | Q2: M1, M2 | R2: Marchés PRF (volets 3 et 5 2026 en cours : ne pas en parler aux acheteurs) ; sourcing R2111-1 ; volets suivants en groupement ; financement Contrat de filière [À VÉRIFIER] | S2: Oui — titulaire = sous-traitant (art. 28) pour les données stagiaires. Contact nominatif : intérêt légitime B2B + information art. 14 au 1er contact. | T2: Sélection/évaluation automatisée de stagiaires = haut risque (annexe III-3), applicable au 02/12/2027 (Omnibus 2026/1744). Art. 50 (transparence) en vigueur depuis le 02/08/2026. | U2: À contacter | X2: centre-inffo.fr (monographies 12/2025 et 03/2026, Contrat Filière Numérique) ; ted.europa.eu ; boamp.fr 26-8510 ; marchesonline.com 2026-DFP-0512
A3: 2 | B3: 1 | C3: France Travail — Direction régionale La Réunion | D3: Financeur public | E3: France Travail (POEI, AFPR, AIF) + OPCO de l'employeur (POEC) | F3: Francicia COURTOIS (Astrid COMBEMOREL, adjointe) | G3: Directrice régionale depuis le 01/04/2026 (adjointe : DR adjointe chargée des opérations) | H3: Bulletin officiel France Travail 2026 (décision DG 2026-3 du 12/01/2026) | I3: Service achats/marchés de la DR + responsables Formation et Relation entreprises [À VÉRIFIER] ; agences locales pour les POEI | J3: Centre d'affaires Cadjee, Bât. C, 62 bd du Chaudron, CS 52008, 97744 Saint-Denis Cedex 9 | K3: 39 95 (employeurs) / 39 49 (candidats) | L3: marches.97410@francetravail.fr (avis BOAMP 2025) — francetravail.fr | M3: Crédits 2026 en baisse de 12 % (subvention 1,16 Md€ vs 1,35 Md€) ; chômage 19 % au T2 2026 (+3 pts en un an) ; loi plein emploi : accompagnement intensif de tous les inscrits. | N3: Madame la Directrice régionale, Avec 19 % de chômage au 2e trimestre et des crédits en baisse de 12 %, chaque euro de formation doit produire une embauche. Je vous propose un dispositif sur 18 mois où j'apporte les deux bouts de la chaîne : les employeurs TPE-PME que je prospecte chaque semaine, avec leurs offres d'emploi, et des parcours courts « relation client + outils IA du quotidien » qui rendent vos candidats opérationnels dès le premier jour. Vous gardez la main sur l'indicateur : un taux de sortie en emploi fixé avec vous et mesuré à 6 mois, cohorte par cohorte. Pouvons-nous en parler 30 minutes avec vos responsables formation et relation entreprises, le … ou le … ? Aurélien LUMEKA — Directeur, YEBA FORMATIONS (Qualiopi 25FOR02027.1 — NDA 04973676397) | O3: « Nos achats sont encadrés / nationaux » → « La POEI et l'AFPR se décident en agence, offre par offre : je vous apporte l'offre d'emploi déjà validée par l'employeur. Vous ne lancez rien : vous signez une embauche. » | P3: « Embauche augmentée 974 » (POEI/POEC) + ateliers recruteurs TPE | Q3: M3, M4 | R3: POEI / AFPR (agence, sur offre d'emploi) ; POEC (avec l'OPCO) ; AIF ; appels à projets régionaux ; marchés FT | S3: Oui — données des candidats (dont RQTH = donnée de santé, art. 9) : convention, minimisation, canal sécurisé. | T3: Profilage/orientation de demandeurs d'emploi = haut risque (annexe III-4 et III-5) au 02/12/2027. | U3: À contacter | X3: bo.francetravail.org (BO 2026) ; assemblee-nationale.fr (CF1896) ; boamp.fr ; insee.fr ; outremers360.com
A4: 3 | B4: 2 | C4: Département de La Réunion (Conseil départemental) | D4: Financeur public | E4: Département (Plan départemental d'insertion) + FSE+ | F4: Cyrille MELCHIOR | G4: Président du Conseil départemental | H4: Wikipédia (non daté) [À VÉRIFIER] | I4: Direction de l'insertion / pilotage du PDI et des appels à projets [À VÉRIFIER] | J4: Hôtel du Département (Palais de la Source), 2 rue de la Source, 97400 Saint-Denis | K4: Non vérifié [À VÉRIFIER] | L4: departement974.fr | M4: Plan d'insertion 2022-2024 : 99 000 actions pour les bénéficiaires du RSA ; loi plein emploi (18/12/2023) : durée d'activité hebdomadaire minimale ; illettrisme ≈ 3 fois la métropole. | N4: Monsieur le Président, La loi pour le plein emploi impose désormais une activité hebdomadaire réelle pour les bénéficiaires du RSA. Le Département a porté 99 000 actions sur son précédent plan d'insertion : le défi n'est plus le volume, c'est la remise en mouvement durable. Je vous propose un parcours de 12 mois, par micro-région, qui combine confiance en soi, codes de l'entreprise et autonomie numérique (smartphone, démarches en ligne, IA pour chercher un emploi), avec une pédagogie par le jeu et des supports accessibles. Indicateur suivi chaque mois : taux de présence et entrées en emploi ou en formation qualifiante. Qui, dans vos services, pilote le prochain appel à projets insertion ? Aurélien LUMEKA — Directeur, YEBA FORMATIONS (Qualiopi 25FOR02027.1 — NDA 04973676397) | O4: « Nous avons déjà des prestataires » → « Je ne remplace personne : je propose un pilote sur un territoire et une cohorte, avec des indicateurs mensuels. Vous comparez sur pièces. » | P4: « Remobilisation & autonomie numérique » bénéficiaires RSA | Q4: M5 | R4: Appels à projets PDI ; pilote < 60 000 € HT sans procédure ; FSE+ [À VÉRIFIER] | S4: Oui — données sociales (RSA), très sensibles : convention de traitement, accès restreint. | T4: Non par défaut. | U4: À contacter | X4: outremers360.com (PDI) ; insee.fr ; monumentum.fr (adresse)
A5: 4 | B5: 2 | C5: DEETS La Réunion (État) | D5: État / prescripteur | E5: État : FSE+ (volet État), PRIC | F5: Arnaud POULY | G5: Directeur de l'économie, de l'emploi, du travail et des solidarités | H5: Acteurs publics (09/2024) + fiche Centre Inffo (02/2026) | I5: Service FSE+ ; mission Mutations économiques ; service contrôle de la formation | J5: 112 rue de la République, 97488 Saint-Denis Cedex | K5: 02 62 94 07 07 | L5: Site de la DEETS (préfecture) [À VÉRIFIER] | M5: Fin/reconfiguration du FNE-Formation et de Transco ; 967 organismes de formation sur l'île ; liste de 63 métiers porteurs à pourvoir. | N5: Monsieur le Directeur, Avec 967 organismes de formation sur l'île et la fin du FNE-Formation, les entreprises en mutation manquent d'interlocuteurs fiables. Je souhaite vous présenter une offre IA & conformité portée par un organisme Qualiopi, Référent handicap, formé par l'ANSSI et la CNIL. Une question précise : parmi vos 63 métiers porteurs, sur lesquels voyez-vous aujourd'hui un manque d'offre ? Je construis la réponse et je la présente à votre service FSE+. Aurélien LUMEKA — Directeur, YEBA FORMATIONS (Qualiopi 25FOR02027.1 — NDA 04973676397) | O5: « Nous ne finançons pas directement » → « Je le sais : je vous demande votre diagnostic, pas un financement. Et la porte d'entrée FSE+ si un appel à projets s'ouvre. » | P5: Veille métiers porteurs + candidature FSE+ | Q5: — | R5: Appels à projets FSE+ [À VÉRIFIER] | S5: Non (organisation). | T5: Non. | U5: À contacter | X5: acteurspublics.fr ; centre-inffo.fr ; choisirleservicepublic.gouv.fr
A6: 5 | B6: 1 | C6: Agefiph — Délégation régionale Réunion-Mayotte | D6: Financeur public | E6: Agefiph (aides à l'adaptation des formations) + Cap emploi | F6: Aïda PERICHON | G6: Déléguée régionale Réunion-Mayotte | H6: Rapport d'activité Agefiph 2025 (publié 07/2026) [À VÉRIFIER] | I6: Délégation régionale — chargés d'études et de développement | J6: Centre d'affaires Cadjee, 62 bd du Chaudron, Bât. C, 2e étage, 97495 Sainte-Clotilde [À VÉRIFIER] | K6: 02 62 20 98 11 [À VÉRIFIER] — national 0 800 11 10 09 | L6: dr974@agefiph.asso.fr [À VÉRIFIER] — agefiph.fr | M6: Démarche « Transform'Action » lancée fin 2025 pour clarifier « qui fait quoi » ; très peu d'organismes de formation réellement accessibles. | N6: Madame la Déléguée régionale, Vous avez lancé Transform'Action pour clarifier qui fait quoi sur le territoire. Je vous propose d'occuper une case encore vide : l'IA et le numérique accessibles. Mes supports sont conçus dès le départ pour la basse vision (gros caractères, mots-clés, contrastes), je suis Référent handicap en organisme de formation, et j'adapte les évaluations. Concrètement : un parcours « IA accessible » de 12 mois pour demandeurs d'emploi et salariés en situation de handicap, co-construit avec Cap emploi. Puis-je vous le présenter le … ou le … ? Aurélien LUMEKA — Directeur, YEBA FORMATIONS (Qualiopi 25FOR02027.1 — NDA 04973676397) | O6: « Nous ne finançons pas des organismes » → « Je ne vous demande pas de me financer : je vous demande de me référencer comme organisme accessible, pour que vos aides individuelles trouvent une offre adaptée. » | P6: « IA accessible » (avec Cap emploi) | Q6: M9 | R6: Aides Agefiph (adaptation des situations de formation) ; appels à projets innovation [À VÉRIFIER] | S6: Oui — handicap = donnée de santé (art. 9) : ne collecter que le nécessaire, base légale explicite. | T6: Non. | U6: À contacter | X6: agefiph.fr (rapport 2025) ; annuaire-administration.com ; fiphfp.fr
A7: 6 | B7: 2 | C7: Transitions Pro La Réunion (ATPro) | D7: Financeur paritaire | E7: Transitions Pro (PTP) | F7: Non identifié [À VÉRIFIER] | G7: Direction | H7: Aucune source trouvée | I7: Service instruction des PTP | J7: Non vérifié — annuaire national transitionspro.fr [À VÉRIFIER] | K7: Non vérifié [À VÉRIFIER] | L7: transitionspro.fr (annuaire) | M7: Budgets contraints, dossiers PTP refusés faute de cohérence projet / formation / métier porteur. | N7: Madame, Monsieur, La DEETS a publié la liste des 63 métiers porteurs, et vos conseillers s'en servent pour orienter les reconversions. Je vous propose des parcours alignés sur cette liste (commercial, assistant IA en entreprise, métiers du numérique), avec un livrable qui sécurise vos dossiers : une promesse d'embauche ou une étude de marché locale par stagiaire. Qui instruit les PTP numériques et commerciaux chez vous ? Aurélien LUMEKA — Directeur, YEBA FORMATIONS (Qualiopi 25FOR02027.1 — NDA 04973676397) | O7: « Nous ne référençons pas d'organismes » → « Je vous demande seulement de connaître l'offre, pour que vos conseillers aient une solution cohérente quand le projet s'y prête. » | P7: Parcours de reconversion « métiers porteurs » | Q7: — | R7: PTP (dossier du salarié) | S7: Oui (données des salariés). | T7: Non. | U7: À contacter | X7: centre-inffo.fr (métiers porteurs)
A8: 7 | B8: 2 | C8: CNFPT — Délégation La Réunion | D8: Fonction publique territoriale | E8: CNFPT (cotisation des collectivités) | F8: Karine AH-SON | G8: Directrice régionale | H8: Page contacts cnfpt.fr (non datée) [À VÉRIFIER] | I8: Conseillers formation (domaine numérique / management) | J8: 4 rue Camille Vergoz, CS 81037, 97404 Saint-Denis Cedex [À VÉRIFIER] | K8: 02 62 90 28 28 [À VÉRIFIER] | L8: cnfpt.fr | M8: Obligations de transparence IA Act depuis le 02/08/2026 ; agents utilisant des IA grand public ; DPO obligatoire dans chaque collectivité (art. 37 RGPD). | N8: Madame la Directrice régionale, Depuis le 2 août 2026, les collectivités sont concernées par les obligations de transparence de l'IA Act, et leurs agents utilisent déjà l'IA, souvent sans cadre. Je vous propose un itinéraire de formation « IA responsable dans le service public local » : gagner du temps sur les courriers et les comptes rendus, sans jamais exposer les données des administrés. Je peux intervenir dès le prochain semestre de votre offre. Quel conseiller formation pilote le domaine numérique ? Aurélien LUMEKA — Directeur, YEBA FORMATIONS (Qualiopi 25FOR02027.1 — NDA 04973676397) | O8: « Notre offre est construite à l'année » → « Alors je vous propose de préparer avec vous la programmation 2027, sur un domaine où la demande des collectivités explose. » | P8: Itinéraire « IA responsable agents territoriaux » | Q8: M7 | R8: Marchés CNFPT / référencement d'intervenants [À VÉRIFIER] | S8: Oui — formation à la protection des données des administrés. | T8: Oui — art. 4 (mesures de maîtrise de l'IA) et art. 50. | U8: À contacter | X8: cnfpt.fr ; annuaire-administration.com
A9: 8 | B9: 1 | C9: CINOR (Nord : Saint-Denis, Sainte-Marie, Sainte-Suzanne) | D9: Collectivité | E9: Budget propre + CNFPT | F9: Jacques LOWINSKY | G9: Président (élu le 08/04/2026) | H9: Outremers 360 (04/2026) | I9: DGS + DPO + DRH | J9: Non vérifié [À VÉRIFIER] | K9: Non vérifié [À VÉRIFIER] | L9: Site officiel [À VÉRIFIER] | M9: Nouvelle mandature ; art. 50 IA Act en vigueur ; DPO obligatoire. | N9: Monsieur le Président, Une nouvelle mandature commence, et elle arrive avec deux obligations très concrètes pour la CINOR : depuis le 2 août 2026, les obligations de transparence de l'IA Act (art. 50) s'appliquent — un chatbot ou un contenu généré par IA mis à disposition du public doit être signalé comme tel ; et le RGPD vous impose déjà un DPO (art. 37). Or, comme dans la plupart des collectivités, des agents utilisent probablement des IA grand public avec des données d'administrés, sans cadre. Je vous propose un « Plan IA responsable » en 90 jours : audit des usages, charte IA validée par votre DPO, formation de vos agents à une IA qui fait gagner du temps sans exposer la collectivité. Le montant reste sous le seuil de 60 000 € HT de dispense de procédure : la décision peut se prendre rapidement, dans le respect de la commande publique. Puis-je présenter ce plan 30 minutes à votre DGS et à votre DPO, le … ou le … ? Aurélien LUMEKA — Directeur, YEBA FORMATIONS (Qualiopi 25FOR02027.1 — NDA 04973676397) | O9: « Nous verrons plus tard / ce n'est pas prioritaire » → « L'art. 50 s'applique depuis le 2 août : plus tard, c'est déjà en retard. Je vous propose de commencer par l'audit des usages (3 jours) : vous saurez exactement où vous êtes exposé. » | P9: Plan IA responsable 90 jours | Q9: M6 | R9: < 60 000 € HT : dispense de procédure (R2122-8, décret 2025-1386) | S9: Oui — DPO obligatoire (art. 37) ; données d'administrés. | T9: Oui — art. 50 et art. 4. | U9: À contacter | X9: outremers360.com
A10: 9 | B10: 1 | C10: Territoire de l'Ouest (ex-TCO) | D10: Collectivité | E10: Budget propre + CNFPT | F10: Emmanuel SÉRAPHIN | G10: Président (réélu le 07/04/2026), maire de Saint-Paul | H10: Communiqué TCO du 07/04/2026 | I10: DGS + DPO + DRH | J10: Non vérifié [À VÉRIFIER] | K10: Non vérifié [À VÉRIFIER] | L10: tco.re | M10: Nouvelle mandature ; art. 50 IA Act en vigueur ; DPO obligatoire. | N10: Monsieur le Président, Une nouvelle mandature commence, et elle arrive avec deux obligations très concrètes pour le Territoire de l'Ouest : depuis le 2 août 2026, les obligations de transparence de l'IA Act (art. 50) s'appliquent — un chatbot ou un contenu généré par IA mis à disposition du public doit être signalé comme tel ; et le RGPD vous impose déjà un DPO (art. 37). Or, comme dans la plupart des collectivités, des agents utilisent probablement des IA grand public avec des données d'administrés, sans cadre. Je vous propose un « Plan IA responsable » en 90 jours : audit des usages, charte IA validée par votre DPO, formation de vos agents à une IA qui fait gagner du temps sans exposer la collectivité. Le montant reste sous le seuil de 60 000 € HT de dispense de procédure : la décision peut se prendre rapidement, dans le respect de la commande publique. Puis-je présenter ce plan 30 minutes à votre DGS et à votre DPO, le … ou le … ? Aurélien LUMEKA — Directeur, YEBA FORMATIONS (Qualiopi 25FOR02027.1 — NDA 04973676397) | O10: « Nous verrons plus tard / ce n'est pas prioritaire » → « L'art. 50 s'applique depuis le 2 août : plus tard, c'est déjà en retard. Je vous propose de commencer par l'audit des usages (3 jours) : vous saurez exactement où vous êtes exposé. » | P10: Plan IA responsable 90 jours | Q10: M6 | R10: < 60 000 € HT : dispense de procédure (R2122-8) | S10: Oui — DPO obligatoire (art. 37). | T10: Oui — art. 50 et art. 4. | U10: À contacter | X10: tco.re ; outremers360.com
A11: 10 | B11: 1 | C11: CIREST (Est) | D11: Collectivité | E11: Budget propre + CNFPT | F11: Joé BÉDIER | G11: Président (élu le 09/04/2026), maire de Saint-André | H11: Outremers 360 (04/2026) | I11: DGS + DPO + DRH | J11: Non vérifié [À VÉRIFIER] | K11: Non vérifié [À VÉRIFIER] | L11: Site officiel [À VÉRIFIER] | M11: Nouvelle mandature (« nouveau chapitre ») ; art. 50 IA Act ; DPO obligatoire. | N11: Monsieur le Président, Une nouvelle mandature commence, et elle arrive avec deux obligations très concrètes pour la CIREST : depuis le 2 août 2026, les obligations de transparence de l'IA Act (art. 50) s'appliquent — un chatbot ou un contenu généré par IA mis à disposition du public doit être signalé comme tel ; et le RGPD vous impose déjà un DPO (art. 37). Or, comme dans la plupart des collectivités, des agents utilisent probablement des IA grand public avec des données d'administrés, sans cadre. Je vous propose un « Plan IA responsable » en 90 jours : audit des usages, charte IA validée par votre DPO, formation de vos agents à une IA qui fait gagner du temps sans exposer la collectivité. Le montant reste sous le seuil de 60 000 € HT de dispense de procédure : la décision peut se prendre rapidement, dans le respect de la commande publique. Puis-je présenter ce plan 30 minutes à votre DGS et à votre DPO, le … ou le … ? Aurélien LUMEKA — Directeur, YEBA FORMATIONS (Qualiopi 25FOR02027.1 — NDA 04973676397) | O11: « Nous verrons plus tard / ce n'est pas prioritaire » → « L'art. 50 s'applique depuis le 2 août : plus tard, c'est déjà en retard. Je vous propose de commencer par l'audit des usages (3 jours) : vous saurez exactement où vous êtes exposé. » | P11: Plan IA responsable 90 jours | Q11: M6 | R11: < 60 000 € HT : dispense de procédure (R2122-8) | S11: Oui — DPO obligatoire (art. 37). | T11: Oui — art. 50 et art. 4. | U11: À contacter | X11: outremers360.com
A12: 11 | B12: 1 | C12: CIVIS (Sud-Ouest) | D12: Collectivité | E12: Budget propre + CNFPT | F12: David LORION | G12: Président (réélu en 2026), maire de Saint-Pierre | H12: Outremers 360 (2026) | I12: DGS + DPO + DRH | J12: Non vérifié [À VÉRIFIER] | K12: Non vérifié [À VÉRIFIER] | L12: civis.re | M12: Nouvelle mandature ; art. 50 IA Act ; DPO obligatoire. | N12: Monsieur le Président, Une nouvelle mandature commence, et elle arrive avec deux obligations très concrètes pour la CIVIS : depuis le 2 août 2026, les obligations de transparence de l'IA Act (art. 50) s'appliquent — un chatbot ou un contenu généré par IA mis à disposition du public doit être signalé comme tel ; et le RGPD vous impose déjà un DPO (art. 37). Or, comme dans la plupart des collectivités, des agents utilisent probablement des IA grand public avec des données d'administrés, sans cadre. Je vous propose un « Plan IA responsable » en 90 jours : audit des usages, charte IA validée par votre DPO, formation de vos agents à une IA qui fait gagner du temps sans exposer la collectivité. Le montant reste sous le seuil de 60 000 € HT de dispense de procédure : la décision peut se prendre rapidement, dans le respect de la commande publique. Puis-je présenter ce plan 30 minutes à votre DGS et à votre DPO, le … ou le … ? Aurélien LUMEKA — Directeur, YEBA FORMATIONS (Qualiopi 25FOR02027.1 — NDA 04973676397) | O12: « Nous verrons plus tard / ce n'est pas prioritaire » → « L'art. 50 s'applique depuis le 2 août : plus tard, c'est déjà en retard. Je vous propose de commencer par l'audit des usages (3 jours) : vous saurez exactement où vous êtes exposé. » | P12: Plan IA responsable 90 jours | Q12: M6 | R12: < 60 000 € HT : dispense de procédure (R2122-8) | S12: Oui — DPO obligatoire (art. 37). | T12: Oui — art. 50 et art. 4. | U12: À contacter | X12: outremers360.com ; civis.re
A13: 12 | B13: 2 | C13: CASUD (Sud) | D13: Collectivité | E13: Budget propre + CNFPT | F13: Non identifié [À VÉRIFIER] | G13: Président(e) | H13: Aucune source trouvée | I13: DGS + DPO + DRH | J13: Non vérifié [À VÉRIFIER] | K13: Non vérifié [À VÉRIFIER] | L13: Site officiel [À VÉRIFIER] | M13: Nouvelle mandature ; art. 50 IA Act ; DPO obligatoire. | N13: Madame, Monsieur le Président, Une nouvelle mandature commence, et elle arrive avec deux obligations très concrètes pour la CASUD : depuis le 2 août 2026, les obligations de transparence de l'IA Act (art. 50) s'appliquent — un chatbot ou un contenu généré par IA mis à disposition du public doit être signalé comme tel ; et le RGPD vous impose déjà un DPO (art. 37). Or, comme dans la plupart des collectivités, des agents utilisent probablement des IA grand public avec des données d'administrés, sans cadre. Je vous propose un « Plan IA responsable » en 90 jours : audit des usages, charte IA validée par votre DPO, formation de vos agents à une IA qui fait gagner du temps sans exposer la collectivité. Le montant reste sous le seuil de 60 000 € HT de dispense de procédure : la décision peut se prendre rapidement, dans le respect de la commande publique. Puis-je présenter ce plan 30 minutes à votre DGS et à votre DPO, le … ou le … ? Aurélien LUMEKA — Directeur, YEBA FORMATIONS (Qualiopi 25FOR02027.1 — NDA 04973676397) | O13: « Nous verrons plus tard / ce n'est pas prioritaire » → « L'art. 50 s'applique depuis le 2 août : plus tard, c'est déjà en retard. Je vous propose de commencer par l'audit des usages (3 jours) : vous saurez exactement où vous êtes exposé. » | P13: Plan IA responsable 90 jours | Q13: M6 | R13: < 60 000 € HT : dispense de procédure (R2122-8) | S13: Oui — DPO obligatoire (art. 37). | T13: Oui — art. 50 et art. 4. | U13: À contacter | X13: —
... A31: 30 | B31: 3 | C31: RSMA-R, E2C, structures d'insertion (SIAE) | D31: Prescripteur / sous-traitance | E31: Selon structure | F31: Non identifié [À VÉRIFIER] | G31: Directions | H31: — | I31: Responsables pédagogiques | J31: Non vérifié [À VÉRIFIER] | K31: Non vérifié [À VÉRIFIER] | L31: — | M31: Publics très éloignés de l'emploi, illettrisme. | N31: Madame, Monsieur, Vos stagiaires ont besoin de reprendre confiance avant d'apprendre un métier. Je vous propose des modules ludiques de savoir-être et d'autonomie numérique, en sous-traitance et en marque blanche si votre contrat l'exige. Qui puis-je rencontrer ? Aurélien LUMEKA — Directeur, YEBA FORMATIONS (Qualiopi 25FOR02027.1 — NDA 04973676397) | O31: — | P31: Sous-traitance soft skills / numérique | Q31: — | R31: Sous-traitance | S31: Oui. | T31: Non. | U31: À contacter | X31: —

Sheet Missions longues
A1: Code | B1: Structure | C1: Intitulé | D1: Durée | E1: Public | F1: Bénéficiaires (nb) | G1: Problème résolu | H1: Contenu | I1: Livrables | J1: Indicateurs de résultat | K1: Voie juridique / financement | L1: Jours d'animation | M1: Jours d'ingénierie | N1: Total jours | O1: Risques & parades
A2: M1 | B2: Région Réunion (+ Digital Réunion) | C2: « IA utile & conforme — TPE-PME 974 » | D2: 24 mois | E2: Dirigeants et salariés de TPE-PME | F2: 480 | G2: Contribuer à l'objectif de 8 000 TPE-PME du Contrat de Filière Numérique avec un résultat mesurable | H2: 40 sessions inter de 2 jours (12 pers.) dans les 4 micro-régions : cas d'usage IA métier, sécurité (ANSSI), RGPD (registre simplifié), IA Act (déployeur, art. 4 et 50) | I2: Cas d'usage IA en production + registre RGPD + charte IA par entreprise ; tableau de bord trimestriel pour la Région | J2: ≥ 80 % des stagiaires ont un cas d'usage IA en production à J+60 ; 100 % repartent avec leur registre ; taux de satisfaction ; part de stagiaires en situation de handicap accueillis | K2: Lot PRF (en groupement si nécessaire) ou financement du Contrat de filière [À VÉRIFIER] | L2: 80 | M2: 10 | N2: =L2+M2 -> 90 | O2: Capacité : 80 jours en 24 mois → s'appuyer sur 1 ou 2 formateurs associés ; groupement avec un OF partenaire
A3: M2 | B3: Région Réunion (agents) | C3: « IA responsable dans le service public régional » | D3: 12 mois | E3: Agents de la Région | F3: 120 | G3: Encadrer les usages IA des agents (art. 4 et 50 IA Act, RGPD) | H3: 10 sessions d'1 jour + rédaction de la charte d'usage IA avec le DPO | I3: Charte IA ; guide des usages autorisés ; 120 agents formés | J3: Charte adoptée ; 0 donnée personnelle saisie dans des IA non validées (audit à 6 mois) | K3: Marché de formation interne de la Région | L3: 10 | M3: 5 | N3: =L3+M3 -> 15 | O3: Valider le périmètre avec le DPO et la DRH
A4: M3 | B4: France Travail | C4: « Embauche augmentée 974 » (POEI / POEC) | D4: 18 mois | E4: Demandeurs d'emploi, sur des offres d'emploi réelles de TPE-PME | F4: 72 | G4: Transformer chaque euro de formation en embauche, avec un chômage à 19 % | H4: 6 cohortes de 12 : relation client, vente, savoir-être, outils IA du quotidien, immersion en entreprise | I4: Promesses d'embauche avant l'entrée ; suivi à 3 et 6 mois | J4: Taux de sortie en emploi à 6 mois (cible fixée avec France Travail) ; abandons < 10 % | K4: POEI / AFPR (agence) ; POEC avec l'OPCO de la branche | L4: 90 | M4: 10 | N4: =L4+M4 -> 100 | O4: Il faut des employeurs engagés AVANT : utiliser votre prospection TPE comme carburant
A5: M4 | B5: France Travail (employeurs) | C5: « Recruter mieux, sans discriminer, avec l'IA » | D5: 12 mois | E5: Dirigeants de TPE qui recrutent | F5: 120 | G5: Recrutements ratés et offres non pourvues dans les TPE | H5: 12 ateliers d'une demi-journée : rédiger une offre, conduire un entretien, ce que l'IA a le droit de faire (IA Act annexe III) | I5: Offre d'emploi réécrite par participant | J5: Offres déposées après l'atelier ; délai de recrutement | K5: Partenariat avec le service entreprises (gratuit pour les TPE) → débouche sur M3 | L5: 6 | M5: 2 | N5: =L5+M5 -> 8 | O5: Format d'apport d'affaires : pas forcément rémunéré
A6: M5 | B6: Département de La Réunion | C6: « Remobilisation & autonomie numérique » | D6: 12 mois | E6: Bénéficiaires du RSA | F6: 96 | G6: Obligation d'activité de la loi plein emploi ; publics éloignés | H6: 4 micro-régions × 2 cohortes de 12 × 10 jours : confiance, codes de l'entreprise, smartphone et démarches, IA pour chercher un emploi | I6: Plan d'action individuel ; bilan mensuel au Département | J6: Présence ≥ 80 % ; entrées en emploi ou formation qualifiante à 6 mois | K6: Appel à projets du PDI ; pilote < 60 000 € HT | L6: 80 | M6: 8 | N6: =L6+M6 -> 88 | O6: Public fragile : pédagogie par le jeu, supports accessibles, prévoir un relais social
A7: M6 | B7: Intercommunalités et communes (×5 EPCI + 24 communes) | C7: « Plan IA responsable — 90 jours » | D7: 3 mois (renouvelable) | E7: Agents, encadrement, élus | F7: 60 | G7: Art. 50 IA Act en vigueur ; DPO obligatoire ; usages IA sans cadre | H7: Audit des usages (3 j) ; charte IA avec le DPO (2 j) ; 6 sessions agents (6 j) ; restitution aux élus (1 j) | I7: Cartographie des usages ; charte ; agents formés ; plan d'action | J7: Charte votée ; usages à risque supprimés ; temps gagné déclaré par les agents | K7: Dispense de procédure < 60 000 € HT (R2122-8) — pas de fractionnement artificiel | L7: 12 | M7: 2 | N7: =L7+M7 -> 14 | O7: Répliquable : 5 EPCI + 24 communes = votre gisement de missions le plus rapide
A8: M7 | B8: CNFPT Réunion | C8: Itinéraire « IA responsable — agents territoriaux » | D8: 12 mois | E8: Agents territoriaux de toutes les collectivités | F8: 120 | G8: Former massivement les agents à un usage sûr de l'IA | H8: 10 sessions de 2 jours | I8: Supports, quiz d'évaluation, fiches réflexes | J8: Satisfaction ; évaluation des acquis | K8: Marchés CNFPT / référencement d'intervenants [À VÉRIFIER] | L8: 20 | M8: 4 | N8: =L8+M8 -> 24 | O8: Calendrier CNFPT annuel : se positionner tôt
A9: M8 | B9: Missions locales (+ Uniformation) | C9: « Conseiller augmenté » | D9: 6 mois | E9: Conseillers des 4 Missions locales | F9: 60 | G9: Crédits en baisse : rendre du temps d'accompagnement aux conseillers | H9: 4 Missions locales × 2 jours : IA pour les comptes rendus, la prospection d'entreprises, le CV des jeunes ; RGPD des jeunes | I9: Kit de prompts validés ; charte | J9: Temps administratif gagné (déclaratif, mesuré avant / après) | K9: Plan de développement des compétences (Uniformation) [À VÉRIFIER] | L9: 8 | M9: 2 | N9: =L9+M9 -> 10 | O9: Ne jamais saisir de données de jeunes dans une IA non validée
A10: M9 | B10: Agefiph + Cap emploi | C10: « IA accessible » | D10: 12 mois | E10: Personnes en situation de handicap (demandeurs d'emploi et salariés) | F10: 32 | G10: Pas d'offre IA réellement accessible | H10: 4 cohortes de 8 × 5 jours, supports basse vision, évaluations adaptées | I10: Parcours et supports accessibles réutilisables | J10: Taux de réussite ; satisfaction ; entrées en emploi | K10: Aides Agefiph + financement de la formation (France Travail, OPCO, CPF) | L10: 20 | M10: 5 | N10: =L10+M10 -> 25 | O10: Données de santé : minimisation
A11: M10 | B11: OPCO + réseaux (CCI, CMA, MEDEF, Les Entrepreneurs, ADIR, CROEC) | C11: Actions collectives et ateliers → intra | D11: 12 mois | E11: Salariés et dirigeants de TPE-PME | F11: 150 | G11: TPE qui ne consomment pas leurs droits | H11: 10 sessions d'1 jour + 6 petits-déjeuners | I11: Check-list conformité ; diagnostics → propositions intra | J11: Nombre de diagnostics → nombre d'intra signés | K11: Plan de développement des compétences ; actions collectives OPCO | L11: 10 | M11: 2 | N11: =L11+M11 -> 12 | O11: Moteur commercial : chaque atelier doit produire des rendez-vous intra

Sheet Chiffrage
A1: Hypothèses (à saisir)
A2: Tarif journalier formateur (€ HT) | B2: 1200 | C2: EXEMPLE — remplacez par votre tarif réel
A3: Seuil de dispense de procédure, services (€ HT) | B3: 60000 | C3: Décret 2025-1386, art. R2122-8 CCP, depuis le 01/04/2026
A5: Mission | B5: Total jours | C5: Bénéficiaires | D5: Montant estimé (€ HT) | E5: Coût / bénéficiaire | F5: Voie d'achat indicative | G5: Intitulé
A6: ='Missions longues'!A2 -> M1 | B6: ='Missions longues'!N2 -> 90 | C6: ='Missions longues'!F2 -> 480 | D6: =B6*$B$2 -> 108000 | E6: =IF(C6>0,D6/C6,0) -> 225 | F6: =IF(D6<$B$3,"Sous le seuil : dispense de procédure possible","Au-dessus du seuil : marché, appel à projets ou dispositif dédié (POEI, AAP…)") -> Au-dessus du seuil : marché, appel à projets ou dispositif dédié (POEI, AAP…) | G6: ='Missions longues'!C2 -> « IA utile & conforme — TPE-PME 974 »
A7: ='Missions longues'!A3 -> M2 | B7: ='Missions longues'!N3 -> 15 | C7: ='Missions longues'!F3 -> 120 | D7: =B7*$B$2 -> 18000 | E7: =IF(C7>0,D7/C7,0) -> 150 | F7: =IF(D7<$B$3,"Sous le seuil : dispense de procédure possible","Au-dessus du seuil : marché, appel à projets ou dispositif dédié (POEI, AAP…)") -> Sous le seuil : dispense de procédure possible | G7: ='Missions longues'!C3 -> « IA responsable dans le service public régional »
A8: ='Missions longues'!A4 -> M3 | B8: ='Missions longues'!N4 -> 100 | C8: ='Missions longues'!F4 -> 72 | D8: =B8*$B$2 -> 120000 | E8: =IF(C8>0,D8/C8,0) -> 1666.6667 | F8: =IF(D8<$B$3,"Sous le seuil : dispense de procédure possible","Au-dessus du seuil : marché, appel à projets ou dispositif dédié (POEI, AAP…)") -> Au-dessus du seuil : marché, appel à projets ou dispositif dédié (POEI, AAP…) | G8: ='Missions longues'!C4 -> « Embauche augmentée 974 » (POEI / POEC)
A9: ='Missions longues'!A5 -> M4 | B9: ='Missions longues'!N5 -> 8 | C9: ='Missions longues'!F5 -> 120 | D9: =B9*$B$2 -> 9600 | E9: =IF(C9>0,D9/C9,0) -> 80 | F9: =IF(D9<$B$3,"Sous le seuil : dispense de procédure possible","Au-dessus du seuil : marché, appel à projets ou dispositif dédié (POEI, AAP…)") -> Sous le seuil : dispense de procédure possible | G9: ='Missions longues'!C5 -> « Recruter mieux, sans discriminer, avec l'IA »
A10: ='Missions longues'!A6 -> M5 | B10: ='Missions longues'!N6 -> 88 | C10: ='Missions longues'!F6 -> 96 | D10: =B10*$B$2 -> 105600 | E10: =IF(C10>0,D10/C10,0) -> 1100 | F10: =IF(D10<$B$3,"Sous le seuil : dispense de procédure possible","Au-dessus du seuil : marché, appel à projets ou dispositif dédié (POEI, AAP…)") -> Au-dessus du seuil : marché, appel à projets ou dispositif dédié (POEI, AAP…) | G10: ='Missions longues'!C6 -> « Remobilisation & autonomie numérique »
A11: ='Missions longues'!A7 -> M6 | B11: ='Missions longues'!N7 -> 14 | C11: ='Missions longues'!F7 -> 60 | D11: =B11*$B$2 -> 16800 | E11: =IF(C11>0,D11/C11,0) -> 280 | F11: =IF(D11<$B$3,"Sous le seuil : dispense de procédure possible","Au-dessus du seuil : marché, appel à projets ou dispositif dédié (POEI, AAP…)") -> Sous le seuil : dispense de procédure possible | G11: ='Missions longues'!C7 -> « Plan IA responsable — 90 jours »
A12: ='Missions longues'!A8 -> M7 | B12: ='Missions longues'!N8 -> 24 | C12: ='Missions longues'!F8 -> 120 | D12: =B12*$B$2 -> 28800 | E12: =IF(C12>0,D12/C12,0) -> 240 | F12: =IF(D12<$B$3,"Sous le seuil : dispense de procédure possible","Au-dessus du seuil : marché, appel à projets ou dispositif dédié (POEI, AAP…)") -> Sous le seuil : dispense de procédure possible | G12: ='Missions longues'!C8 -> Itinéraire « IA responsable — agents territoriaux »
A13: ='Missions longues'!A9 -> M8 | B13: ='Missions longues'!N9 -> 10 | C13: ='Missions longues'!F9 -> 60 | D13: =B13*$B$2 -> 12000 | E13: =IF(C13>0,D13/C13,0) -> 200 | F13: =IF(D13<$B$3,"Sous le seuil : dispense de procédure possible","Au-dessus du seuil : marché, appel à projets ou dispositif dédié (POEI, AAP…)") -> Sous le seuil : dispense de procédure possible | G13: ='Missions longues'!C9 -> « Conseiller augmenté »
A14: ='Missions longues'!A10 -> M9 | B14: ='Missions longues'!N10 -> 25 | C14: ='Missions longues'!F10 -> 32 | D14: =B14*$B$2 -> 30000 | E14: =IF(C14>0,D14/C14,0) -> 937.5 | F14: =IF(D14<$B$3,"Sous le seuil : dispense de procédure possible","Au-dessus du seuil : marché, appel à projets ou dispositif dédié (POEI, AAP…)") -> Sous le seuil : dispense de procédure possible | G14: ='Missions longues'!C10 -> « IA accessible »
A15: ='Missions longues'!A11 -> M10 | B15: ='Missions longues'!N11 -> 12 | C15: ='Missions longues'!F11 -> 150 | D15: =B15*$B$2 -> 14400 | E15: =IF(C15>0,D15/C15,0) -> 96 | F15: =IF(D15<$B$3,"Sous le seuil : dispense de procédure possible","Au-dessus du seuil : marché, appel à projets ou dispositif dédié (POEI, AAP…)") -> Sous le seuil : dispense de procédure possible | G15: ='Missions longues'!C11 -> Actions collectives et ateliers → intra
A16: TOTAL | B16: =SUM(B6:B15) -> 386 | C16: =SUM(C6:C15) -> 1310 | D16: =SUM(D6:D15) -> 463200
A18: Attention : le seuil s'apprécie par besoin homogène de l'acheteur, sur la durée du contrat. Découper une mission pour rester sous le seuil est interdit (fractionnement). Les prix PRF sont souvent fixés à l'heure-stagiaire : convertissez avant de candidater.

Sheet OPCO
A1: OPCO | B1: Secteurs couverts | C1: Présence à La Réunion | D1: Contact identifié | E1: Angle YEBA FORMATIONS | F1: Site
A2: AKTO | B2: Services à forte intensité de main-d'œuvre : hôtellerie-restauration, propreté, sécurité privée, travail temporaire… | C2: Présent à La Réunion ; gère aussi Atlas et OPCO 2i par délégation (conventions renouvelées au 01/01/2026) | D2: François HAQUIN, directeur régional (2022-2023) [À VÉRIFIER] | E2: Vente additionnelle, accueil, IA pour les avis clients | F2: akto.fr
A3: OPCO EP | B3: Entreprises de proximité : artisanat, commerce de proximité, professions libérales (54 branches) | C3: Implantations à Sainte-Clotilde et Saint-Leu ; +15 % DROM sur le coût pédagogique (fiche 2025) [À VÉRIFIER] | D3: Brice VIRGINIUS, délégué régional (03/2025) [À VÉRIFIER] — 0 970 838 837 | E3: IA gain de temps + RGPD fichier clients | F3: opcoep.fr
A4: Atlas | B4: Banque, assurance, conseil, numérique, cabinets d'experts-comptables | C4: Service de proximité assuré par AKTO à La Réunion | D4: Via AKTO | E4: IA en cabinet, IA Act / RGPD | F4: akto.fr ; opco-atlas.fr [À VÉRIFIER]
A5: OPCO 2i | B5: Industrie (métallurgie, chimie, plasturgie…) | C5: Conseil et gestion assurés par AKTO à La Réunion | D5: Via AKTO | E5: Management de proximité + IA en atelier | F5: akto.fr
A6: Constructys | B6: Bâtiment et travaux publics | C6: Association régionale paritaire à La Réunion (autorisation outre-mer 2018-2020) | D6: Non identifié [À VÉRIFIER] | E6: Management de chantier + IA devis / comptes rendus | F6: constructys.fr
A7: OCAPIAT | B7: Agriculture, pêche, agroalimentaire, coopératives | C7: Autorisé à intervenir à La Réunion (arrêté du 29/05/2019) | D7: Non identifié [À VÉRIFIER] | E7: Vente directe + IA communication | F7: ocapiat.fr [À VÉRIFIER]
A8: AFDAS | B8: Culture, médias, sport, loisirs | C8: Autorisé à intervenir à La Réunion (arrêté du 29/05/2019) | D8: Non identifié [À VÉRIFIER] | E8: Communication + IA générative (droits d'auteur, art. 50) | F8: afdas.com [À VÉRIFIER]
A9: Uniformation | B9: Économie sociale et solidaire, associations, cohésion sociale (dont Missions locales) | C9: Ligne Réunion-Mayotte 02 62 56 78 78 (2019) [À VÉRIFIER] | D9: Non identifié [À VÉRIFIER] | E9: « Conseiller augmenté », RGPD associations | F9: uniformation.fr
A10: OPCO Santé | B10: Santé privée, médico-social privé | C10: Présence locale non confirmée [À VÉRIFIER] | D10: Non identifié [À VÉRIFIER] | E10: IA et données de santé : ce qui est interdit | F10: opco-sante.fr [À VÉRIFIER]
A11: OPCO Mobilités | B11: Transport, services de l'automobile | C11: Présence locale non confirmée [À VÉRIFIER] | D11: Non identifié [À VÉRIFIER] | E11: Relation client + IA planning | F11: opcomobilites.fr [À VÉRIFIER]
A12: L'Opcommerce | B12: Commerce de détail et de gros | C12: Agréé pour intervenir directement outre-mer ; déléguée territoriale | D12: Anne-Laure HOARAU, déléguée territoriale [À VÉRIFIER] | E12: Vente en magasin + fidélisation IA | F12: lopcommerce.com [À VÉRIFIER]
A14: COMMENT TROUVER L'OPCO D'UNE ENTREPRISE (en 2 minutes)
A15: 1. Demandez l'IDCC (numéro de convention collective) : il figure sur le bulletin de paie. L'IDCC détermine l'OPCO.
A16: 2. Sans convention collective : l'OPCO dépend de l'activité principale (code NAF / APE, visible sur l'avis SIRENE).
A17: 3. Confirmez en appelant l'OPCO avec le SIRET : c'est lui qui dit oui ou non au financement, selon les critères de la branche.
A18: 4. Moins de 50 salariés : le plan de développement des compétences est financé par l'OPCO, sous réserve des fonds disponibles.
A19: 5. Argument CPF : si l'employeur abonde, le salarié ne paie pas le reste à charge de 150 € (depuis le 02/04/2026).

Sheet Preuves
A1: Fait | B1: Chiffre / élément | C1: Date | D1: Source (URL) | E1: Comment l'utiliser
A2: Chômage BIT à La Réunion | B2: 16 % en 2025 (plus bas historique) → 19 % au T2 2026 | C2: 2026 | D2: https://www.insee.fr/fr/statistiques/8966940 ; https://outremers360.com/bassin-indien-appli/la-reunion-le-taux-de-chomage-augmente-et-atteint-19-de-la-population-active-au-deuxieme-trimestre-2026-selon-linsee | E2: Ouverture de rendez-vous : France Travail, Région, Département
A3: Crédits France Travail 2026 | B3: -12 % vs 2025 ; subvention 1,16 Md€ vs 1,35 Md€ | C3: 2026 | D3: https://www.assemblee-nationale.fr/dyn/17/amendements/1906C/CION_FIN/CF1896.pdf | E3: « Chaque euro doit produire une embauche »
A4: Contrat de Filière Numérique 2026-2028 | B4: Signé le 18/02/2026 ; 8 000 TPE-PME à transformer ; 10 000 usagers vers l'autonomie numérique | C4: 02/2026 | D4: https://www.centre-inffo.fr/site-regions-formation/actualites-regions/la-reunion-signe-le-contrat-de-filiere-numerique-2026-2028 | E4: Votre argument n°1 auprès de la Région et de Digital Réunion
A5: Dépenses régionales de formation | B5: 70,3 M€ (2022) → 113,8 M€ (2024) ; 967 organismes de formation (10/2025) | C5: 03/2026 | D5: https://www.centre-inffo.fr/content/uploads/2026/03/monographie-formation-professionnelle-apprentissage-et-emploi-la-reunion-mars-2026.pdf | E5: Exigence de résultats + différenciation
A6: Marchés PRF 2026 | B6: Volet 3 : 22 lots, lot 2 jusqu'à 3,88 M€ / 24 mois, critère prix ; volet 5 (2026-DFP-0512) : 4 lots, lot 2 jusqu'à 1,47 M€ HT | C6: 2026 | D6: https://www.boamp.fr/telechargements/FILES/PDF/2026/01/26-8510.pdf ; https://www.marchesonline.com/appels-offres/avis/programme-regional-de-formation-professionnelle-a-bons/ao-9638543-1 | E6: Surveiller les prochains volets ; préparer un groupement
A7: Seuil de dispense de procédure (services) | B7: 60 000 € HT depuis le 01/04/2026 (décret 2025-1386, art. R2122-8) | C7: 04/2026 | D7: https://blog.landot-avocats.net/2026/04/01/marches-publics-relevement-du-seuil-de-dispense-de-procedure-a-60-000-e-des-aujourdhui/ | E7: Missions M6 auprès des collectivités : décision rapide possible
A8: IA Act — Omnibus (règlement UE 2026/1744) | B8: En vigueur le 27/07/2026 ; art. 4 réécrit (obligation de prendre des mesures) ; haut risque annexe III reporté au 02/12/2027 ; art. 50 (transparence) applicable au 02/08/2026 | C8: 07/2026 | D8: https://spicyadvisory.com/blog/digital-omnibus-ai-act-2026-what-changed ; https://aiactinsight.eu/fr/ai-act/digital-omnibus/ | E8: Ne plus dire « obligation de former tous les salariés » ; dire « obligation de prendre des mesures » + art. 50. Vérifier sur EUR-Lex.
A9: CPF : reste à charge | B9: 150 € depuis le 02/04/2026 (sauf demandeurs d'emploi et abondement employeur) | C9: 04/2026 | D9: https://www.editions-tissot.fr/actualite/droit-du-travail/cpf-le-reste-a-charge-passe-a-150-euros-a-compter-du-2-avril-2026 | E9: TPE : « si vous abondez, votre salarié ne paie pas les 150 € »
A10: Missions locales | B10: 28 153 jeunes accompagnés en 2025, 14 769 sorties ; crédits d'État -15 % environ en 2025-2026 ; nouvelle baisse au PLF 2027 | C10: 10/2026 | D10: https://outremers360.com/bassin-indien-appli/les-elus-des-missions-locales-de-la-reunion-et-mayotte-reclament-le-maintien-de-leurs-financements-pour-2027-en-faveur-de-linsertion-des-jeunes ; https://www.banquedesterritoires.fr/les-missions-locales-vont-elles-aussi-devoir-contribuer-aux-economies-budgetaires | E10: Proposer du financement hors de leur enveloppe
A11: Jeunes NEET / illettrisme | B11: 26 % de NEET (2021) ; illettrisme ≈ 3 × la métropole | C11: 2021 | D11: https://www.insee.fr/fr/statistiques/fichier/8639740/re_inc_39.pdf | E11: Pédagogie ludique et accessible
A12: Plan départemental d'insertion | B12: 99 000 actions prévues sur 2022-2024 | C12: — | D12: https://outremers360.com/bassin-indien-appli/la-reunion-amplification-de-laccompagnement-des-beneficiaires-du-rsa-bilan-et-perspectives-du-plan-departemental-dinsertion | E12: Département
... A16: Agefiph Réunion | B16: Démarche Transform'Action (fin 2025) : clarifier « qui fait quoi » | C16: 07/2026 | D16: https://www.agefiph.fr/sites/default/files/medias/fichiers/2026-07/Agefiph-Reunion_Rapport-activite_2025.pdf | E16: Agefiph
